Workbook

Sheet Raw_data
A1: Rank | B1: Title | C1: Year | D1: Genre | E1: Director | F1: Cast | G1: Language | H1: Plot | I1: Awards | J1: Production | K1: Flickmetrix_Score | L1: IMDb_10 | M1: IMDb_100 | N1: IMDb_Votes | O1: Metacritic | P1: Critic_Rating_RT | Q1: Critic_Reviews | R1: Audience_Rating | S1: Audience_Reviews | T1: Letterboxd | U1: Letterboxd_Votes | V1: Google_Score | W1: Streaming_On | X1: RT_URL | Y1: imdbID | Z1: Custom_Score
A2: 1 | B2: The Godfather | C2: 1972 | D2: Drama, Crime | E2: Francis Ford Coppola | F2: Marlon Brando, Al Pacino, James Caan, Robert Duvall | G2: en | H2: Spanning the years 1945 to 1955, a chronicle of the fictional Italian-American Corleone crime family. When organized crime family patriarch, Vito Corleone barely survives an attempt on his life, his youngest son, Michael steps in to take care of the would-be killers, launching a campaign of bloody revenge. | I2: Won 3 Oscars. Another 30 wins & 19 nominations. | J2: Paramount Pictures | K2: 93.0 | L2: 46062 | M2: 92.0 | N2: 2108796 | O2: 100.0 | P2: 96.0 | Q2: 104 | R2: 95.0 | S2: 1087289.0 | T2: 90 | U2: 1789555.0 | V2: 90.0 | W2: paramount, itunes, amzvid | X2: https://www.rottentomatoes.com/m/godfather | Y2: tt0068646 | Z2: 93.83
A3: 2 | B3: Seven Samurai | C3: 1954 | D3: Action, Drama | E3: Akira Kurosawa | F3: Toshir≈ç Mifune, Takashi Shimura, Yoshio Inaba, Seiji Miyaguchi | G3: ja | H3: A samurai answers a village's request for protection after he falls on hard times. The town needs protection from bandits, so the samurai gathers six others to help him teach the people how to defend themselves, and the villagers provide the soldiers with food. | I3: Nominated for 2 Oscars. Another 6 wins & 5 nominations. | J3: Columbia Pictures | K3: 93.0 | L3: 46181 | M3: 86.0 | N3: 381712 | O3: 98.0 | P3: 97.0 | Q3: 68 | R3: 94.0 | S3: 167123.0 | T3: 92 | U3: 318537.0 | V3: 93.0 | W3: hbo, itunes, amzvid, hbm | X3: https://www.rottentomatoes.com/m/seven_samurai_1956 | Y3: tt0047478 | Z3: 93.33
A4: 3 | B4: 12 Angry Men | C4: 1957 | D4: Drama | E4: Sidney Lumet | F4: Martin Balsam, John Fiedler, Lee J. Cobb, E.G. Marshall | G4: en | H4: The defense and the prosecution have rested and the jury is filing into the jury room to decide if a young Spanish-American is guilty or innocent of murdering his father. What begins as an open and shut case soon becomes a mini-drama of each of the jurors' prejudices and preconceptions about the trial, the accused, and each other. | I4: Nominated for 3 Oscars. Another 16 wins & 8 nominations. | J4: Criterion Collection | K4: 92.0 | L4: 9.0 | M4: 90.0 | N4: 917215 | O4: 97.0 | P4: 93.0 | Q4: 58 | R4: 94.0 | S4: 376697.0 | T4: 92 | U4: 917590.0 | V4: 91.0 | W4: itunes, amzvid | X4: https://www.rottentomatoes.com/m/1000013_12_angry_men | Y4: tt0050083 | Z4: 92.83
A5: 4 | B5: Schindler's List | C5: 1993 | D5: Drama, History, War | E5: Steven Spielberg | F5: Liam Neeson, Ben Kingsley, Ralph Fiennes, Caroline Goodall | G5: en | H5: The true story of how businessman Oskar Schindler saved over a thousand Jewish lives from the Nazis while they worked as slaves in his factory during World War II. | I5: Won 7 Oscars. Another 74 wins & 26 nominations. | J5: Universal Pictures | K5: 92.0 | L5: 9.0 | M5: 90.0 | N5: 1512905 | O5: 95.0 | P5: 93.0 | Q5: 82 | R5: 94.0 | S5: 601555.0 | T5: 90 | U5: 978054.0 | V5: 93.0 | W5: itunes, amzvid | X5: https://www.rottentomatoes.com/m/schindlers_list | Y5: tt0108052 | Z5: 92.5
A6: 5 | B6: The Godfather: Part II | C6: 1974 | D6: Drama, Crime | E6: Francis Ford Coppola | F6: Al Pacino, Robert Duvall, Diane Keaton, Robert De Niro | G6: en | H6: In the continuing saga of the Corleone crime family, a young Vito Corleone grows up in Sicily and in 1910s New York. In the 1950s, Michael Corleone attempts to expand the family business into Las Vegas, Hollywood and Cuba. | I6: Won 6 Oscars. Another 13 wins & 16 nominations. | J6: Paramount Pictures | K6: 92.0 | L6: 9.0 | M6: 90.0 | N6: 1420179 | O6: 90.0 | P6: 95.0 | Q6: 80 | R6: 94.0 | S6: 586600.0 | T6: 92 | U6: 934120.0 | V6: 89.0 | W6: paramount, itunes, amzvid | X6: https://www.rottentomatoes.com/m/godfather_part_ii/ | Y6: tt0071562 | Z6: 91.67
A7: 6 | B7: Rear Window | C7: 1954 | D7: Thriller, Mystery | E7: Alfred Hitchcock | F7: James Stewart, Grace Kelly, Wendell Corey, Thelma Ritter | G7: en | H7: A wheelchair-bound photographer spies on his neighbors from his apartment window and becomes convinced one of them has committed murder. | I7: Nominated for 4 Oscars. Another 7 wins & 7 nominations. | J7: Paramount Pictures | K7: 91.0 | L7: 46150 | M7: 85.0 | N7: 542959 | O7: 100.0 | P7: 95.0 | Q7: 94 | R7: 92.0 | S7: 303476.0 | T7: 88 | U7: 607614.0 | V7: 90.0 | W7: itunes, amzvid | X7: https://www.rottentomatoes.com/m/1017289-rear_window | Y7: tt0047396 | Z7: 91.67
A8: 7 | B8: Pulp Fiction | C8: 1994 | D8: Thriller, Crime | E8: Quentin Tarantino | F8: John Travolta, Samuel L. Jackson, Uma Thurman, Bruce Willis | G8: en | H8: A burger-loving hit man, his philosophical partner, a drug-addled gangster's moll and a washed-up boxer converge in this sprawling, comedic crime caper. Their adventures unfurl in three stories that ingeniously trip back and forth in time. | I8: Won 1 Oscar. Another 63 wins & 47 nominations. | J8: Miramax Films | K8: 91.0 | L8: 46273 | M8: 89.0 | N8: 2319136 | O8: 95.0 | P8: 94.0 | Q8: 132 | R8: 93.0 | S8: 1731042.0 | T8: 86 | U8: 2931535.0 | V8: 92.0 | W8: paramount, peacock, itunes, amzvid, hbm | X8: https://www.rottentomatoes.com/m/pulp_fiction/ | Y8: tt0110912 | Z8: 91.5
A9: 8 | B9: City Lights | C9: 1931 | D9: Comedy, Drama, Romance | E9: Charlie Chaplin | F9: Charlie Chaplin, Virginia Cherrill, Florence Lee, Harry Myers | G9: en | H9: A tramp falls in love with a beautiful blind flower girl. His on-and-off friendship with a wealthy man allows him to be the girl's benefactor and suitor. | I9: 3 wins. | J9: Twentieth Century Fox Home Entertainment | K9: 91.0 | L9: 46150 | M9: 85.0 | N9: 205619 | O9: 99.0 | P9: 94.0 | Q9: 52 | R9: 92.0 | S9: 66173.0 | T9: 86 | U9: 144013.0 | V9: 92.0 | W9: itunes, amzvid, hbm | X9: https://www.rottentomatoes.com/m/city_lights | Y9: tt0021749 | Z9: 91.33
A10: 9 | B10: Spirited Away | C10: 2001 | D10: Animation, Family, Fantasy | E10: Hayao Miyazaki | F10: Rumi Hiiragi, Miyu Irino, Mari Natsuki, Takashi Naito | G10: ja | H10: A young girl, Chihiro, becomes trapped in a strange new world of spirits. When her parents undergo a mysterious transformation, she must call upon the courage she never knew she had to free her family. | I10: Won 1 Oscar. Another 51 wins & 22 nominations. | J10: Walt Disney Pictures | K10: 90.0 | L10: 46181 | M10: 86.0 | N10: 901217 | O10: 96.0 | P10: 89.0 | Q10: 134 | R10: 93.0 | S10: 1052053.0 | T10: 88 | U10: 2478980.0 | V10: 95.0 | W10: itunes, amzvid, hbm | X10: https://www.rottentomatoes.com/m/spirited_away | Y10: tt0245429 | Z10: 91.17
A11: 10 | B11: Parasite | C11: 2019 | D11: Comedy, Thriller, Drama | E11: Bong Joon Ho | F11: Song Kang-ho, Lee Sun-kyun, Cho Yeo-jeong, Choi Woo-shik | G11: ko | H11: All unemployed, Ki-taek's family takes peculiar interest in the wealthy and glamorous Parks for their livelihood until they get entangled in an unexpected incident. | K11: 91.0 | L11: 46150 | M11: 85.0 | N11: 1050592 | O11: 97.0 | P11: 95.0 | Q11: 314 | R11: 88.0 | S11: 1273882.0 | T11: 90 | U11: 3771374.0 | V11: 90.0 | W11: itunes, amzvid | X11: https://www.rottentomatoes.com/m/parasite_2019 | Y11: tt6751668 | Z11: 90.83
A12: 11 | B12: Modern Times | C12: 1936 | D12: Comedy, Drama, Romance | E12: Charlie Chaplin | F12: Charlie Chaplin, Paulette Goddard, Henry Bergman, Tiny Sandford | G12: en | H12: A bumbling tramp desires to build a home with a young woman, yet is thwarted time and time again by his lack of experience and habit of being in the wrong place at the wrong time.. | I12: 3 wins & 1 nomination. | J12: United Artists | K12: 90.0 | L12: 46150 | M12: 85.0 | N12: 271086 | O12: 96.0 | P12: 95.0 | Q12: 72 | R12: 92.0 | S12: 97048.0 | T12: 86 | U12: 210247.0 | V12: 90.0 | W12: prime, itunes, amzvid, hbm | Y12: tt0027977 | Z12: 90.67
A13: 12 | B13: Goodfellas | C13: 1990 | D13: Drama, Crime | E13: Martin Scorsese | F13: Robert De Niro, Ray Liotta, Joe Pesci, Lorraine Bracco | G13: en | H13: The true story of Henry Hill, a half-Irish, half-Sicilian Brooklyn kid who is adopted by neighbourhood gangsters at an early age and climbs the ranks of a Mafia family under the guidance of Jimmy Conway. | I13: Won 1 Oscar. Another 42 wins & 24 nominations. | J13: Warner Bros. | K13: 90.0 | L13: 46211 | M13: 87.0 | N13: 1315490 | O13: 92.0 | P13: 91.0 | Q13: 95 | R13: 94.0 | S13: 766130.0 | T13: 90 | U13: 1435501.0 | V13: 89.0 | W13: prime, itunes, amzvid, hbm | X13: https://www.rottentomatoes.com/m/1032176-goodfellas/ | Y13: tt0099685 | Z13: 90.5
A14: 13 | B14: The Good, the Bad and the Ugly | C14: 1966 | D14: Western | E14: Sergio Leone | F14: Clint Eastwood, Eli Wallach, Lee Van Cleef, Aldo Giuffr√® | G14: it | H14: While the Civil War rages on between the Union and the Confederacy, three men ‚Äì a quiet loner, a ruthless hitman, and a Mexican bandit ‚Äì comb the American Southwest in search of a strongbox containing $200,000 in stolen gold. | I14: 1 win. | J14: United Artists | K14: 89.0 | L14: 46242 | M14: 88.0 | N14: 847249 | O14: 90.0 | P14: 89.0 | Q14: 58 | R14: 94.0 | S14: 328668.0 | T14: 90 | U14: 504912.0 | V14: 91.0 | W14: itunes, amzvid | X14: https://www.rottentomatoes.com/m/the_good_the_bad_and_the_ugly | Y14: tt0060196 | Z14: 90.33
A15: 14 | B15: Dr. Strangelove or: How I Learned to Stop Worrying and Love the Bomb | C15: 1964 | D15: Comedy, War | E15: Stanley Kubrick | F15: Peter Sellers, George C. Scott, Sterling Hayden, Keenan Wynn | G15: en | H15: After the insane General Jack D. Ripper initiates a nuclear strike on the Soviet Union, a war room full of politicians, generals and a Russian diplomat all frantically try to stop the nuclear strike. | I15: Nominated for 4 Oscars. Another 15 wins & 4 nominations. | J15: Sony Pictures | K15: 90.0 | L15: 46089 | M15: 83.0 | N15: 535648 | O15: 97.0 | P15: 93.0 | Q15: 87 | R15: 90.0 | S15: 298335.0 | T15: 86 | U15: 475057.0 | V15: 92.0 | W15: itunes, amzvid | X15: https://www.rottentomatoes.com/m/dr_strangelove | Y15: tt0057012 | Z15: 90.17
A16: 15 | B16: Casablanca | C16: 1942 | D16: Drama, Romance | E16: Michael Curtiz | F16: Humphrey Bogart, Ingrid Bergman, Paul Henreid, Claude Rains | G16: en | H16: In Casablanca, Morocco in December 1941, a cynical American expatriate meets a former lover, with unforeseen complications. | I16: Won 3 Oscars. Another 6 wins & 6 nominations. | J16: Warner Bros. Pictures | K16: 90.0 | L16: 46150 | M16: 85.0 | N16: 628003 | O16: 100.0 | P16: 96.0 | Q16: 96 | R16: 91.0 | S16: 429846.0 | T16: 86 | U16: 572792.0 | V16: 83.0 | W16: hbo, itunes, amzvid, hbm | X16: https://www.rottentomatoes.com/m/1003707_casablanca | Y16: tt0034583 | Z16: 90.17
A17: 16 | B17: The Battle of Algiers | C17: 1966 | D17: Drama, War, History | E17: Gillo Pontecorvo | F17: Brahim Hadjadj, Yacef Sa√¢di, Fouzia El Kader, Jean Martin | G17: it | H17: Tracing the struggle of the Algerian Front de Liberation Nationale to gain freedom from French colonial rule as seen through the eyes of Ali from his start as a petty thief to his rise to prominence in the organisation and capture by the French in 1957. The film traces the rebels' struggle and the increasingly extreme measures taken by the French government to quell the revolt. | I17: Nominated for 3 Oscars. Another 11 wins & 3 nominations. | J17: Rialto Pictures | K17: 90.0 | L17: 46030 | M17: 81.0 | N17: 70309 | O17: 96.0 | P17: 92.0 | Q17: 67 | R17: 91.0 | S17: 37316.0 | T17: 88 | U17: 82844.0 | V17: 92.0 | W17: itunes, amzvid, hbm | X17: https://www.rottentomatoes.com/m/the_battle_of_algiers | Y17: tt0058946 | Z17: 90.0
A18: 17 | B18: Singin' in the Rain | C18: 1952 | D18: Comedy, Romance | E18: Stanley Donen, Gene Kelly | F18: Gene Kelly, Donald O'Connor, Debbie Reynolds, Jean Hagen | G18: en | H18: In 1927 Hollywood, a silent film production company and cast make a difficult transition to sound. | I18: Nominated for 2 Oscars. Another 5 wins & 7 nominations. | J18: MGM | K18: 90.0 | L18: 46089 | M18: 83.0 | N18: 270897 | O18: 99.0 | P18: 95.0 | Q18: 62 | R18: 91.0 | S18: 242729.0 | T18: 86 | U18: 450117.0 | V18: 86.0 | W18: hbo, itunes, amzvid, hbm | X18: https://www.rottentomatoes.com/m/singin_in_the_rain/ | Y18: tt0045152 | Z18: 90.0
A19: 18 | B19: Some Like It Hot | C19: 1959 | D19: Comedy, Romance, Crime | E19: Billy Wilder | F19: Tony Curtis, Jack Lemmon, Marilyn Monroe, George Raft | G19: en | H19: Two musicians witness a mob hit and struggle to find a way out of the city before they are found by the gangsters. Their only opportunity is to join an all-girl band as they leave on a tour. To make their getaway they must first disguise themselves as women, then keep their identities secret and deal with the problems this brings - such as an attractive bandmate and a very determined suitor. | I19: Won 1 Oscar. Another 9 wins & 13 nominations. | J19: United Artists | K19: 89.0 | L19: 46061 | M19: 82.0 | N19: 293363 | O19: 98.0 | P19: 93.0 | Q19: 77 | R19: 90.0 | S19: 143114.0 | T19: 86 | U19: 264180.0 | V19: 90.0 | W19: prime, itunes, amzvid | X19: https://www.rottentomatoes.com/m/some_like_it_hot/ | Y19: tt0053291 | Z19: 89.83
A20: 19 | B20: Psycho | C20: 1960 | D20: Horror, Thriller, Mystery | E20: Alfred Hitchcock | F20: Anthony Perkins, Janet Leigh, Vera Miles, John Gavin | G20: en | H20: When larcenous real estate clerk Marion Crane goes on the lam with a wad of cash and hopes of starting a new life, she ends up at the notorious Bates Motel, where manager Norman Bates cares for his housebound mother. | I20: Nominated for 4 Oscars. Another 7 wins & 5 nominations. | J20: Paramount Pictures | K20: 89.0 | L20: 46150 | M20: 85.0 | N20: 748078 | O20: 97.0 | P20: 94.0 | Q20: 97 | R20: 92.0 | S20: 491167.0 | T20: 86 | U20: 991319.0 | V20: 85.0 | W20: itunes, amzvid | X20: https://www.rottentomatoes.com/m/psycho/ | Y20: tt0054215 | Z20: 89.83
A21: 20 | B21: Apocalypse Now | C21: 1979 | D21: Drama, War | E21: Francis Ford Coppola | F21: Martin Sheen, Marlon Brando, Albert Hall, Frederic Forrest | G21: en | H21: At the height of the Vietnam war, Captain Benjamin Willard is sent on a dangerous mission that, officially, "does not exist, nor will it ever exist." His goal is to locate - and eliminate - a mysterious Green Beret Colonel named Walter Kurtz, who has been leading his personal army on illegal guerrilla missions into enemy territory. | I21: Won 2 Oscars. Another 20 wins & 30 nominations. | J21: United Artists | K21: 89.0 | L21: 46120 | M21: 84.0 | N21: 737539 | O21: 94.0 | P21: 92.0 | Q21: 117 | R21: 91.0 | S21: 429279.0 | T21: 88 | U21: 714063.0 | V21: 89.0 | W21: itunes, amzvid | X21: https://www.rottentomatoes.com/m/apocalypse_now/ | Y21: tt0078788 | Z21: 89.67
A22: 21 | B22: Double Indemnity | C22: 1944 | D22: Crime, Thriller | E22: Billy Wilder | F22: Fred MacMurray, Barbara Stanwyck, Edward G. Robinson, Porter Hall | G22: en | H22: A rich woman and a calculating insurance agent plot to kill her unsuspecting husband after he signs a double indemnity policy. | I22: Nominated for 7 Oscars. Another 2 wins & 2 nominations. | J22: Paramount Pictures | K22: 89.0 | L22: 46089 | M22: 83.0 | N22: 173790 | O22: 95.0 | P22: 93.0 | Q22: 72 | R22: 91.0 | S22: 79935.0 | T22: 86 | U22: 167927.0 | V22: 89.0 | W22: prime, itunes, amzvid | X22: https://www.rottentomatoes.com/m/double_indemnity | Y22: tt0036775 | Z22: 89.5
A23: 22 | B23: Rashomon | C23: 1950 | D23: Crime, Drama, Mystery | E23: Akira Kurosawa | F23: Toshir≈ç Mifune, Machiko Ky≈ç, Takashi Shimura, Masayuki Mori | G23: ja | H23: Brimming with action while incisively examining the nature of truth, "Rashomon" is perhaps the finest film ever to investigate the philosophy of justice. Through an ingenious use of camera and flashbacks, Kurosawa reveals the complexities of human nature as four people recount different versions of the story of a man's murder and the rape of his wife. | K23: 89.0 | L23: 46061 | M23: 82.0 | N23: 188349 | O23: 98.0 | P23: 94.0 | Q23: 52 | R23: 90.0 | S23: 105423.0 | T23: 84 | U23: 219549.0 | V23: 88.0 | W23: itunes, amzvid, hbm | X23: https://www.rottentomatoes.com/m/rashomon | Y23: tt0042876 | Z23: 89.33
A24: 23 | B24: Lawrence of Arabia | C24: 1962 | D24: Adventure, History, War | E24: David Lean | F24: Peter O'Toole, Alec Guinness, Anthony Quinn, Jack Hawkins | G24: en | H24: The story of British officer T.E. Lawrence's mission to aid the Arab tribes in their revolt against the Ottoman Empire during the First World War. Lawrence becomes a flamboyant, messianic figure in the cause of Arab unity but his psychological instability threatens to undermine his achievements. | I24: Won 7 Oscars. Another 22 wins & 15 nominations. | J24: Columbia Pictures | K24: 89.0 | L24: 46089 | M24: 83.0 | N24: 327276 | O24: 100.0 | P24: 96.0 | Q24: 82 | R24: 89.0 | S24: 129761.0 | T24: 88 | U24: 238330.0 | V24: 80.0 | W24: itunes, amzvid | X24: https://www.rottentomatoes.com/m/lawrence_of_arabia | Y24: tt0056172 | Z24: 89.33
A25: 24 | B25: All About Eve | C25: 1950 | D25: Drama | E25: Joseph L. Mankiewicz | F25: Bette Davis, Anne Baxter, George Sanders, Celeste Holm | G25: en | H25: From the moment she glimpses her idol at the stage door, Eve Harrington is determined to take the reins of power away from the great actress Margo Channing. Eve maneuvers her way into Margo's Broadway role, becomes a sensation and even causes turmoil in the lives of Margo's director boyfriend, her playwright and his wife. Only the cynical drama critic sees through Eve, admiring her audacity and perfect pattern of deceit. | I25: Won 6 Oscars. Another 16 wins & 17 nominations. | J25: 20th Century Fox | K25: 89.0 | L25: 46061 | M25: 82.0 | N25: 143727 | O25: 98.0 | P25: 95.0 | Q25: 73 | R25: 90.0 | S25: 66740.0 | T25: 88 | U25: 109394.0 | V25: 83.0 | W25: itunes, amzvid | X25: https://www.rottentomatoes.com/m/1000626_all_about_eve | Y25: tt0042192 | Z25: 89.33
A26: 25 | B26: Portrait of a Lady on Fire | C26: 2019 | D26: Drama, Romance, History | E26: C√©line Sciamma | F26: No√©mie Merlant, Ad√®le Haenel, Lu√†na Bajrami, Valeria Golino | G26: fr | H26: On an isolated island in Brittany at the end of the eighteenth century, a female painter is obliged to paint a wedding portrait of a young woman. | K26: 89.0 | L26: 46030 | M26: 81.0 | N26: 117917 | O26: 95.0 | P26: 91.0 | Q26: 197 | R26: 89.0 | S26: 275015.0 | T26: 88 | U26: 819613.0 | V26: 91.0 | W26: itunes | X26: https://www.rottentomatoes.com/m/portrait_of_a_lady_on_fire | Y26: tt8613070 | Z26: 89.17
A27: 26 | B27: A Separation | C27: 2011 | D27: Drama | E27: Asghar Farhadi | F27: Leila Hatami, Payman Maadi, Sareh Bayat, Sarina Farhadi | G27: fa | H27: A married couple are faced with a difficult decision - to improve the life of their child by moving to another country or to stay in Iran and look after a deteriorating parent who has Alzheimer's disease. | I27: Won 1 Oscar. Another 84 wins & 30 nominations. | J27: Sony Pictures Classics | K27: 89.0 | L27: 46089 | M27: 83.0 | N27: 267944 | O27: 95.0 | P27: 91.0 | Q27: 117 | R27: 88.0 | S27: 62517.0 | T27: 88 | U27: 141543.0 | V27: 89.0 | W27: itunes, amzvid | X27: https://www.rottentomatoes.com/m/a_separation_2011 | Y27: tt1832382 | Z27: 89.0
A28: 27 | B28: One Battle After Another | C28: 2025 | D28: Action, Thriller, Crime | E28: Paul Thomas Anderson | F28: Leonardo DiCaprio, Sean Penn, Chase Infiniti, Benicio del Toro | G28: en | H28: Washed-up revolutionary Bob exists in a state of stoned paranoia, surviving off-grid with his spirited, self-reliant daughter, Willa. When his evil nemesis resurfaces after 16 years and she goes missing, the former radical scrambles to find her, father and daughter both battling the consequences of his past. | K28: 89.0 | L28: 46061 | M28: 82.0 | N28: 115333 | O28: 95.0 | P28: 91.0 | Q28: 211 | T28: 88 | X28: https://www.rottentomatoes.com/m/one_battle_after_another | Y28: tt30144839 | Z28: 89.0
A29: 28 | B29: The Lord of the Rings: The Return of the King | C29: 2003 | D29: Adventure, Fantasy, Action | E29: Peter Jackson | F29: Elijah Wood, Ian McKellen, Viggo Mortensen, Sean Astin | G29: en | H29: As armies mass for a final battle that will decide the fate of the world--and powerful, ancient forces of Light and Dark compete to determine the outcome--one member of the Fellowship of the Ring is revealed as the noble heir to the throne of the Kings of Men. Yet, the sole hope for triumph over evil lies with a brave hobbit, Frodo, who, accompanied by his loyal friend Sam and the hideous, wretched Gollum, ventures deep into the very dark heart of Mordor on his seemingly impossible quest to destroy the Ring of Power.‚Äã | I29: Won 11 Oscars. Another 164 wins & 87 nominations. | J29: New Line Cinema | K29: 89.0 | L29: 9.0 | M29: 90.0 | N29: 2064721 | O29: 94.0 | P29: 89.0 | Q29: 172 | R29: 85.0 | S29: 23617405.0 | T29: 90 | U29: 1492669.0 | V29: 85.0 | W29: hbo, itunes, amzvid, hbm | X29: https://www.rottentomatoes.com/m/the_lord_of_the_rings_the_return_of_the_king/ | Y29: tt0167260 | Z29: 88.83
A30: 29 | B30: Citizen Kane | C30: 1941 | D30: Mystery, Drama | E30: Orson Welles | F30: Orson Welles, Joseph Cotten, Dorothy Comingore, Ray Collins | G30: en | H30: Newspaper magnate Charles Foster Kane is taken from his mother as a boy and made the ward of a rich industrialist. As a result, every well-meaning, tyrannical or self-destructive move he makes for the rest of his life appears in some way to be a reaction to that deeply wounding event. | I30: Won 1 Oscar. Another 8 wins & 10 nominations. | J30: RKO Radio Pictures | K30: 89.0 | L30: 46089 | M30: 83.0 | N30: 478970 | O30: 100.0 | P30: 98.0 | Q30: 96 | R30: 87.0 | S30: 273099.0 | T30: 84 | U30: 499118.0 | V30: 81.0 | W30: itunes, amzvid, hbm | X30: https://www.rottentomatoes.com/m/citizen_kane/ | Y30: tt0033467 | Z30: 88.83
A31: 30 | B31: Metropolis | C31: 1927 | D31: Drama, Science Fiction | E31: Fritz Lang | F31: Gustav Fr√∂hlich, Brigitte Helm, Alfred Abel, Rudolf Klein-Rogge | G31: de | H31: In a futuristic city sharply divided between the rich and the poor, the son of the city's mastermind meets a prophet who predicts the coming of a savior to mediate their differences. | I31: 3 wins & 4 nominations. | J31: Paramount Pictures | K31: 88.0 | L31: 46089 | M31: 83.0 | N31: 193052 | O31: 98.0 | P31: 93.0 | Q31: 99 | R31: 89.0 | S31: 108894.0 | T31: 86 | U31: 200533.0 | V31: 84.0 | W31: itunes, amzvid | X31: https://www.rottentomatoes.com/m/1013775-metropolis | Y31: tt0017136 | Z31: 88.83
A32: 31 | B32: It's a Wonderful Life | C32: 1946 | D32: Drama, Family, Fantasy | E32: Frank Capra | F32: James Stewart, Donna Reed, Lionel Barrymore, Thomas Mitchell | G32: en | H32: A holiday favourite for generations... George Bailey has spent his entire life giving to the people of Bedford Falls. All that prevents rich skinflint Mr. Potter from taking over the entire town is George's modest building and loan company. But on Christmas Eve the business's $8,000 is lost and George's troubles begin. | I32: Nominated for 5 Oscars. Another 7 wins. | J32: Liberty Films | K32: 88.0 | L32: 46181 | M32: 86.0 | N32: 524890 | O32: 89.0 | P32: 90.0 | Q32: 75 | R32: 92.0 | S32: 320749.0 | T32: 88 | U32: 522501.0 | V32: 88.0 | W32: prime, itunes, amzvid | X32: https://www.rottentomatoes.com/m/1010792_its_a_wonderful_life | Y32: tt0038650 | Z32: 88.83
A33: 32 | B33: Sunset Blvd. | C33: 1950 | D33: Drama | E33: Billy Wilder | F33: William Holden, Gloria Swanson, Erich von Stroheim, Nancy Olson | G33: en | H33: A hack screenwriter writes a screenplay for a former silent film star who has faded into Hollywood obscurity. | I33: Won 3 Oscars. Another 19 wins & 14 nominations. | J33: Paramount Pictures | K33: 88.0 | L33: 46120 | M33: 84.0 | N33: 247384 | O33: 94.0 | P33: 95.0 | Q33: 89 | R33: 92.0 | S33: 123301.0 | T33: 88 | U33: 262498.0 | V33: 80.0 | W33: itunes, amzvid | X33: https://www.rottentomatoes.com/m/sunset_boulevard | Y33: tt0043014 | Z33: 88.83
A34: 33 | B34: The Lord of the Rings: The Fellowship of the Ring | C34: 2001 | D34: Adventure, Fantasy, Action | E34: Peter Jackson | F34: Elijah Wood, Ian McKellen, Viggo Mortensen, Sean Astin | G34: en | H34: Young hobbit Frodo Baggins, after inheriting a mysterious ring from his uncle Bilbo, must leave his home in order to keep it from falling into the hands of its evil creator. Along the way, a fellowship is formed to protect the ringbearer and make sure that the ring arrives at its final destination: Mt. Doom, the only place where it can be destroyed. | I34: Won 4 Oscars. Another 110 wins & 100 nominations. | J34: New Line Cinema | K34: 87.0 | L34: 46273 | M34: 89.0 | N34: 2094033 | O34: 92.0 | P34: 85.0 | Q34: 142 | R34: 92.0 | S34: 1546965.0 | T34: 88 | U34: 1929394.0 | V34: 86.0 | W34: hbo, itunes, amzvid, hbm | X34: https://www.rottentomatoes.com/m/the_lord_of_the_rings_the_fellowship_of_the_ring/ | Y34: tt0120737 | Z34: 88.67
A35: 34 | B35: North by Northwest | C35: 1959 | D35: Thriller, Adventure | E35: Alfred Hitchcock | F35: Cary Grant, Eva Marie Saint, James Mason, Jessie Royce Landis | G35: en | H35: Advertising man Roger Thornhill is mistaken for a spy, triggering a deadly cross-country chase. | I35: Nominated for 3 Oscars. Another 8 wins & 4 nominations. | J35: Turner Entertainment | K35: 88.0 | L35: 46089 | M35: 83.0 | N35: 358883 | O35: 98.0 | P35: 94.0 | Q35: 90 | R35: 90.0 | S35: 142001.0 | T35: 84 | U35: 265857.0 | V35: 83.0 | W35: itunes, amzvid, hbm | X35: https://www.rottentomatoes.com/m/north_by_northwest? | Y35: tt0053125 | Z35: 88.67
A36: 35 | B36: The Apartment | C36: 1960 | D36: Comedy, Drama, Romance | E36: Billy Wilder | F36: Jack Lemmon, Shirley MacLaine, Fred MacMurray, Ray Walston | G36: en | H36: Bud Baxter is a minor clerk in a huge New York insurance company, until he discovers a quick way to climb the corporate ladder. He lends out his apartment to the executives as a place to take their mistresses. Although he often has to deal with the aftermath of their visits, one night he's left with a major problem to solve. | I36: Won 5 Oscars. Another 19 wins & 8 nominations. | J36: United Artists | K36: 88.0 | L36: 46089 | M36: 83.0 | N36: 207527 | O36: 94.0 | P36: 90.0 | Q36: 93 | R36: 91.0 | S36: 109780.0 | T36: 88 | U36: 252510.0 | V36: 86.0 | W36: itunes, amzvid | X36: https://www.rottentomatoes.com/m/1001115-apartment | Y36: tt0053604 | Z36: 88.67
A37: 36 | B37: One Flew Over the Cuckoo's Nest | C37: 1975 | D37: Drama | E37: Milo≈° Forman | F37: Jack Nicholson, Brad Dourif, Louise Fletcher, Danny DeVito | G37: en | H37: A petty criminal fakes insanity to serve his sentence in a mental ward rather than prison. He soon finds himself as a leader to the other patients‚Äîand an enemy to the cruel, domineering nurse who runs the ward. | I37: Won 5 Oscars. Another 31 wins & 12 nominations. | J37: United Artists | K37: 88.0 | L37: 46211 | M37: 87.0 | N37: 1110492 | O37: 84.0 | P37: 89.0 | Q37: 91 | R37: 93.0 | S37: 421045.0 | T37: 88 | U37: 702258.0 | V37: 91.0 | W37: itunes | X37: https://www.rottentomatoes.com/m/one_flew_over_the_cuckoos_nest | Y37: tt0073486 | Z37: 88.67
A38: 37 | B38: Star Wars: Episode V - The Empire Strikes Back | C38: 1980 | D38: Adventure, Action, Science Fiction | E38: Irvin Kershner | F38: Mark Hamill, Harrison Ford, Carrie Fisher, Billy Dee Williams | G38: en | H38: The epic saga continues as Luke Skywalker, in hopes of defeating the evil Galactic Empire, learns the ways of the Jedi from aging master Yoda. But Darth Vader is more determined than ever to capture Luke. Meanwhile, rebel leader Princess Leia, cocky Han Solo, Chewbacca, and droids C-3PO and R2-D2 are thrown into various stages of capture, betrayal and despair. | I38: Won 1 Oscar. Another 15 wins & 17 nominations. | J38: Twentieth Century Fox | K38: 88.0 | L38: 46211 | M38: 87.0 | N38: 1431491 | O38: 82.0 | P38: 88.0 | Q38: 81 | R38: 93.0 | S38: 1214408.0 | T38: 88 | U38: 1521674.0 | V38: 94.0 | W38: disney, itunes, amzvid | X38: https://www.rottentomatoes.com/m/empire_strikes_back | Y38: tt0080684 | Z38: 88.67
A39: 38 | B39: Whiplash | C39: 2014 | D39: Drama, Music | E39: Damien Chazelle | F39: Miles Teller, J.K. Simmons, Paul Reiser, Melissa Benoist | G39: en | H39: Under the direction of a ruthless instructor, a talented young drummer begins to pursue perfection at any cost, even his humanity. | I39: Won 3 Oscars. Another 87 wins & 99 nominations. | J39: Sony Pictures Classics | K39: 88.0 | L39: 46150 | M39: 85.0 | N39: 1063607 | O39: 89.0 | P39: 87.0 | Q39: 231 | R39: 91.0 | S39: 1025887.0 | T39: 88 | U39: 2932518.0 | V39: 92.0 | W39: itunes, amzvid | X39: https://www.rottentomatoes.com/m/whiplash_2014 | Y39: tt2582802 | Z39: 88.67
A40: 39 | B40: Vertigo | C40: 1958 | D40: Mystery, Romance, Thriller | E40: Alfred Hitchcock | F40: James Stewart, Kim Novak, Barbara Bel Geddes, Tom Helmore | G40: en | H40: A retired San Francisco detective suffering from acrophobia investigates the strange activities of an old friend's wife, all the while becoming dangerously obsessed with her. | I40: Nominated for 2 Oscars. Another 8 wins & 3 nominations. | J40: Paramount Pictures | K40: 88.0 | L40: 46089 | M40: 83.0 | N40: 442662 | O40: 100.0 | P40: 92.0 | Q40: 78 | R40: 90.0 | S40: 267419.0 | T40: 84 | U40: 596103.0 | V40: 83.0 | W40: itunes, amzvid | X40: https://www.rottentomatoes.com/m/vertigo | Y40: tt0052357 | Z40: 88.67
A41: 40 | B41: Bicycle Thieves | C41: 1948 | D41: Drama | E41: Vittorio De Sica | F41: Lamberto Maggiorani, Enzo Staiola, Lianella Carell, Gino Saltamerenda | G41: it | H41: Unemployed Antonio is elated when he finally finds work hanging posters around war-torn Rome. However on his first day, his bicycle‚Äîessential to his work‚Äîgets stolen. His job is doomed unless he can find the thief. With the help of his son, Antonio combs the city, becoming desperate for justice. | I41: Nominated for 1 Oscar. Another 18 wins. | J41: ENIC | K41: 87.0 | L41: 46061 | M41: 82.0 | N41: 184016 | P41: 93.0 | Q41: 58 | R41: 91.0 | S41: 93336.0 | T41: 86 | U41: 211270.0 | V41: 91.0 | W41: itunes, amzvid, hbm | X41: https://www.rottentomatoes.com/m/bicycle_thieves | Y41: tt0040522 | Z41: 88.6
A42: 41 | B42: Ran | C42: 1985 | D42: Action, Drama, History | E42: Akira Kurosawa | F42: Tatsuya Nakadai, Akira Terao, Jinpachi Nezu, Daisuke Ry≈´ | G42: ja | H42: With Ran, legendary director Akira Kurosawa reimagines Shakespeare's King Lear as a singular historical epic set in sixteenth-century Japan. Majestic in scope, the film is Kurosawa's late-life masterpiece, a profound examination of the folly of war and the crumbling of one family under the weight of betrayal, greed, and the insatiable thirst for power. | I42: Won 1 Oscar. Another 29 wins & 18 nominations. | J42: Rialto Pictures | K42: 88.0 | L42: 46061 | M42: 82.0 | N42: 142429 | O42: 97.0 | P42: 92.0 | Q42: 73 | R42: 91.0 | S42: 80147.0 | T42: 90 | U42: 163420.0 | V42: 79.0 | W42: itunes, amzvid | X42: https://www.rottentomatoes.com/m/ran | Y42: tt0089881 | Z42: 88.5
A43: 42 | B43: Pan's Labyrinth | C43: 2006 | D43: Fantasy, Drama, War | E43: Guillermo del Toro | F43: Ivana Baquero, Sergi L√≥pez, Maribel Verd√∫, Ariadna Gil | G43: es | H43: Living with her tyrannical stepfather in a new home with her pregnant mother, 10-year-old Ofelia feels alone until she explores a decaying labyrinth guarded by a mysterious faun who claims to know her destiny. If she wishes to return to her real father, Ofelia must complete three terrifying tasks. | I43: Won 3 Oscars. Another 103 wins & 72 nominations. | J43: Picturehouse | K43: 88.0 | L43: 46061 | M43: 82.0 | N43: 721982 | O43: 98.0 | P43: 89.0 | Q43: 164 | R43: 87.0 | S43: 672087.0 | T43: 84 | U43: 741536.0 | V43: 91.0 | W43: itunes, amzvid | X43: https://www.rottentomatoes.com/m/pans_labyrinth | Y43: tt0457430 | Z43: 88.5
A44: 43 | B44: The Third Man | C44: 1949 | D44: Thriller, Mystery | E44: Carol Reed | F44: Joseph Cotten, Alida Valli, Trevor Howard, Orson Welles | G44: en | H44: In postwar Vienna, Austria, Holly Martins, a writer of pulp Westerns, arrives penniless as a guest of his childhood chum Harry Lime, only to learn he has died. Martins develops a conspiracy theory after learning of a "third man" present at the time of Harry's death, running into interference from British officer Major Calloway, and falling head-over-heels for Harry's grief-stricken lover, Anna. | I44: Won 1 Oscar. Another 4 wins & 4 nominations. | J44: Rialto Pictures | K44: 88.0 | L44: 46030 | M44: 81.0 | N44: 188727 | O44: 97.0 | P44: 95.0 | Q44: 81 | R44: 89.0 | S44: 86513.0 | T44: 86 | U44: 151068.0 | V44: 83.0 | W44: prime, itunes, amzvid | X44: https://www.rottentomatoes.com/m/the_third_man | Y44: tt0041959 | Z44: 88.5
A45: 44 | B45: Star Wars: Episode IV - A New Hope | C45: 1977 | D45: Adventure, Action, Science Fiction | E45: George Lucas | F45: Mark Hamill, Harrison Ford, Carrie Fisher, Peter Cushing | G45: en | H45: Princess Leia is captured and held hostage by the evil Imperial forces in their effort to take over the galactic Empire. Venturesome Luke Skywalker and dashing captain Han Solo team together with the loveable robot duo R2-D2 and C-3PO to rescue the beautiful princess and restore peace and justice in the Empire. | I45: Won 6 Oscars. Another 38 wins & 27 nominations. | J45: 20th Century Fox | K45: 88.0 | L45: 46181 | M45: 86.0 | N45: 1498734 | O45: 90.0 | P45: 89.0 | Q45: 99 | R45: 92.0 | S45: 1163061.0 | T45: 84 | U45: 1758149.0 | V45: 90.0 | W45: disney, itunes, amzvid | X45: https://www.rottentomatoes.com/m/star_wars | Y45: tt0076759 | Z45: 88.5
A46: 45 | B46: 12 Years a Slave | C46: 2013 | D46: Drama, History | E46: Steve McQueen | F46: Chiwetel Ejiofor, Michael Fassbender, Lupita Nyong'o, Benedict Cumberbatch | G46: en | H46: In the pre-Civil War United States, Solomon Northup, a free black man from upstate New York, is abducted and sold into slavery. Facing cruelty as well as unexpected kindnesses Solomon struggles not only to stay alive, but to retain his dignity. In the twelfth year of his unforgettable odyssey, Solomon‚Äôs chance meeting with a Canadian abolitionist will forever alter his life. | K46: 88.0 | L46: 46030 | M46: 81.0 | N46: 761724 | O46: 96.0 | P46: 91.0 | Q46: 244 | R46: 87.0 | S46: 278959.0 | T46: 84 | U46: 554833.0 | V46: 91.0 | W46: itunes, amzvid, hbm | X46: https://www.rottentomatoes.com/m/12_years_a_slave/ | Y46: tt2024544 | Z46: 88.33
A47: 46 | B47: Saving Private Ryan | C47: 1998 | D47: Drama, History, War | E47: Steven Spielberg | F47: Tom Hanks, Tom Sizemore, Edward Burns, Barry Pepper | G47: en | H47: As U.S. troops storm the beaches of Normandy, three brothers lie dead on the battlefield, with a fourth trapped behind enemy lines. Ranger captain John Miller and seven men are tasked with penetrating German-held territory and bringing the boy home. | I47: Won 5 Oscars. Another 78 wins & 66 nominations. | J47: Paramount Pictures | K47: 88.0 | L47: 46181 | M47: 86.0 | N47: 1559687 | O47: 91.0 | P47: 87.0 | Q47: 91 | R47: 91.0 | S47: 1004841.0 | T47: 84 | U47: 1024759.0 | V47: 91.0 | W47: netflix, prime, paramount, itunes, amzvid | X47: https://www.rottentomatoes.com/m/saving_private_ryan/ | Y47: tt0120815 | Z47: 88.33
A48: 47 | B48: WALL¬∑E | C48: 2008 | D48: Animation, Family, Science Fiction | E48: Andrew Stanton | F48: Ben Burtt, Elissa Knight, Jeff Garlin, Fred Willard | G48: en | H48: What if mankind had to leave Earth and somebody forgot to turn the last robot off? After hundreds of years doing what he was built for, WALL‚Ä¢E discovers a new purpose in life when he meets a sleek search robot named EVE. EVE comes to realize that WALL‚Ä¢E has inadvertently stumbled upon the key to the planet's future, and races back to space to report to the humans. Meanwhile, WALL‚Ä¢E chases EVE across the galaxy and sets into motion one of the most imaginative adventures ever brought to the big screen. | I48: Won 1 Oscar. Another 84 wins & 65 nominations. | J48: Walt Disney Pictures | K48: 88.0 | L48: 46120 | M48: 84.0 | N48: 1252363 | O48: 95.0 | P48: 88.0 | Q48: 152 | R48: 87.0 | S48: 1014430.0 | T48: 84 | U48: 1843873.0 | V48: 92.0 | W48: disney, itunes, amzvid | X48: https://www.rottentomatoes.com/m/wall_e | Y48: tt0910970 | Z48: 88.33
A49: 48 | B49: Alien | C49: 1979 | D49: Horror, Science Fiction | E49: Ridley Scott | F49: Tom Skerritt, Sigourney Weaver, Veronica Cartwright, Harry Dean Stanton | G49: en | H49: During its return to the earth, commercial spaceship Nostromo intercepts a distress signal from a distant planet. When a three-member team of the crew discovers a chamber containing thousands of eggs on the planet, a creature inside one of the eggs attacks an explorer. The entire crew is unaware of the impending nightmare set to descend upon them when the alien parasite planted inside its unfortunate host is birthed. | I49: Won 1 Oscar. Another 15 wins & 19 nominations. | J49: 20th Century Fox | K49: 88.0 | L49: 46150 | M49: 85.0 | N49: 1009344 | O49: 89.0 | P49: 91.0 | Q49: 139 | R49: 91.0 | S49: 764014.0 | T49: 86 | U49: 1368049.0 | V49: 88.0 | W49: hbo, itunes, amzvid | X49: https://www.rottentomatoes.com/m/alien | Y49: tt0078748 | Z49: 88.33
A50: 49 | B50: The 400 Blows | C50: 1959 | D50: Drama | E50: Fran√ßois Truffaut | F50: Jean-Pierre L√©aud, Claire Maurier, Albert R√©my, Georges Flamant | G50: fr | H50: For young Parisian boy Antoine Doinel, life is one difficult situation after another. Surrounded by inconsiderate adults, including his neglectful parents, Antoine spends his days with his best friend, Rene, trying to plan for a better life. When one of their schemes goes awry, Antoine ends up in trouble with the law, leading to even more conflicts with unsympathetic authority figures. | I50: Nominated for 1 Oscar. Another 7 wins & 3 nominations. | J50: Zenith International Films | K50: 87.0 | L50: 8.0 | M50: 80.0 | N50: 131044 | P50: 95.0 | Q50: 66 | R50: 90.0 | S50: 98670.0 | T50: 86 | U50: 218210.0 | V50: 90.0 | W50: itunes, amzvid, hbm | X50: https://www.rottentomatoes.com/m/400_blows | Y50: tt0053198 | Z50: 88.2
A51: 50 | B51: The Silence of the Lambs | C51: 1991 | D51: Crime, Drama, Thriller | E51: Jonathan Demme | F51: Jodie Foster, Anthony Hopkins, Scott Glenn, Ted Levine | G51: en | H51: Clarice Starling is a top student at the FBI's training academy. Jack Crawford wants Clarice to interview Dr. Hannibal Lecter, a brilliant psychiatrist who is also a violent psychopath, serving life behind bars for various acts of murder and cannibalism. Crawford believes that Lecter may have insight into a case and that Starling, as an attractive young woman, may be just the bait to draw him out. | I51: Won 5 Oscars. Another 51 wins & 30 nominations. | J51: Orion Pictures Corporation | K51: 87.0 | L51: 46181 | M51: 86.0 | N51: 1622286 | O51: 86.0 | P51: 88.0 | Q51: 112 | R51: 92.0 | S51: 1226259.0 | T51: 86 | U51: 1981219.0 | V51: 91.0 | W51: itunes, amzvid | X51: https://www.rottentomatoes.com/m/silence_of_the_lambs/ | Y51: tt0102926 | Z51: 88.17
A52: 51 | B52: Back to the Future | C52: 1985 | D52: Adventure, Comedy, Science Fiction | E52: Robert Zemeckis | F52: Michael J. Fox, Christopher Lloyd, Crispin Glover, Lea Thompson | G52: en | H52: Eighties teenager Marty McFly is accidentally sent back in time to 1955, inadvertently disrupting his parents' first meeting and attracting his mother's romantic interest. Marty must repair the damage to history by rekindling his parents' romance and - with the help of his eccentric inventor friend Doc Brown - return to 1985. | I52: Won 1 Oscar. Another 18 wins & 24 nominations. | J52: Universal Pictures | K52: 88.0 | L52: 46150 | M52: 85.0 | N52: 1367504 | O52: 87.0 | P52: 89.0 | Q52: 79 | R52: 91.0 | S52: 1322805.0 | T52: 84 | U52: 1773760.0 | V52: 93.0 | W52: itunes, amzvid | X52: https://www.rottentomatoes.com/m/back_to_the_future | Y52: tt0088763 | Z52: 88.17
A53: 52 | B53: Taxi Driver | C53: 1976 | D53: Crime, Drama | E53: Martin Scorsese | F53: Robert De Niro, Jodie Foster, Cybill Shepherd, Harvey Keitel | G53: en | H53: A mentally unstable Vietnam War veteran works as a night-time taxi driver in New York City where the perceived decadence and sleaze feed his urge for violent action. | I53: Nominated for 4 Oscars. Another 27 wins & 9 nominations. | J53: Columbia Pictures | K53: 87.0 | L53: 46061 | M53: 82.0 | N53: 970967 | O53: 94.0 | P53: 92.0 | Q53: 103 | R53: 90.0 | S53: 719732.0 | T53: 82 | U53: 1635079.0 | V53: 88.0 | W53: itunes, amzvid | X53: https://www.rottentomatoes.com/m/taxi_driver | Y53: tt0075314 | Z53: 88.0
A54: 53 | B54: Touch of Evil | C54: 1958 | D54: Crime, Thriller, Mystery, Drama | E54: Orson Welles | F54: Charlton Heston, Janet Leigh, Orson Welles, Joseph Calleia | G54: en | H54: When a car bomb explodes on the American side of the U.S./Mexico border, Mexican drug enforcement agent Miguel Vargas begins his investigation, along with American police captain Hank Quinlan. When Vargas begins to suspect that Quinlan and his shady partner, Menzies, are planting evidence to frame an innocent man, his investigations into their possible corruption quickly put himself and his new bride, Susie, in jeopardy. | K54: 87.0 | L54: 46272 | M54: 79.0 | N54: 112253 | O54: 99.0 | P54: 92.0 | Q54: 64 | R54: 88.0 | S54: 49794.0 | T54: 84 | U54: 86695.0 | V54: 86.0 | W54: itunes, amzvid | X54: https://www.rottentomatoes.com/m/1021749_touch_of_evil | Y54: tt0052311 | Z54: 88.0
A55: 54 | B55: The Pianist | C55: 2002 | D55: Drama, War | E55: Roman Polanski | F55: Adrien Brody, Thomas Kretschmann, Frank Finlay, Maureen Lipman | G55: en | H55: The true story of pianist W≈Çadys≈Çaw Szpilman's experiences in Warsaw during the Nazi occupation. When the Jews of the city find themselves forced into a ghetto, Szpilman finds work playing in a caf√©; and when his family is deported in 1942, he stays behind, works for a while as a laborer, and eventually goes into hiding in the ruins of the war-torn city. | I55: Won 3 Oscars. Another 50 wins & 61 nominations. | J55: Focus Features | K55: 87.0 | L55: 46150 | M55: 85.0 | N55: 961695 | O55: 85.0 | P55: 83.0 | Q55: 104 | R55: 93.0 | S55: 457473.0 | T55: 88 | U55: 864540.0 | V55: 94.0 | W55: amzvid | X55: https://www.rottentomatoes.com/m/pianist | Y55: tt0253474 | Z55: 88.0
A56: 55 | B56: Toy Story | C56: 1995 | D56: Animation, Adventure, Family, Comedy | E56: John Lasseter | F56: Tom Hanks, Tim Allen, Don Rickles, Jim Varney | G56: en | H56: Led by Woody, Andy's toys live happily in his room until Andy's birthday brings Buzz Lightyear onto the scene. Afraid of losing his place in Andy's heart, Woody plots against Buzz. But when circumstances separate Buzz and Woody from their owner, the duo eventually learns to put aside their differences. | I56: Nominated for 3 Oscars. Another 23 wins & 14 nominations. | J56: Buena Vista | K56: 88.0 | L56: 46089 | M56: 83.0 | N56: 1115033 | O56: 96.0 | P56: 92.0 | Q56: 73 | R56: 89.0 | S56: 1290101.0 | T56: 82 | U56: 1651887.0 | V56: 86.0 | W56: disney, itunes, amzvid | X56: https://www.rottentomatoes.com/m/toy_story/ | Y56: tt0114709 | Z56: 88.0
A57: 56 | B57: Raiders of the Lost Ark | C57: 1981 | D57: Adventure, Action | E57: Steven Spielberg | F57: Harrison Ford, Karen Allen, Paul Freeman, John Rhys-Davies | G57: en | H57: When Dr. Indiana Jones ‚Äì the tweed-suited professor who just happens to be a celebrated archaeologist ‚Äì is hired by the government to locate the legendary Ark of the Covenant, he finds himself up against the entire Nazi regime. | I57: Won 4 Oscars. Another 28 wins & 22 nominations. | J57: Paramount Pictures | K57: 88.0 | L57: 46120 | M57: 84.0 | N57: 1068716 | O57: 86.0 | P57: 91.0 | Q57: 105 | R57: 91.0 | S57: 869164.0 | T57: 84 | U57: 949820.0 | V57: 91.0 | W57: disney, paramount, itunes, amzvid | X57: https://www.rottentomatoes.com/m/raiders_of_the_lost_ark/ | Y57: tt0082971 | Z57: 87.83
A58: 57 | B58: The Lives of Others | C58: 2006 | D58: Drama, Thriller | E58: Florian Henckel von Donnersmarck | F58: Martina Gedeck, Ulrich M√ºhe, Sebastian Koch, Ulrich Tukur | G58: de | H58: In 1983 East Berlin, dedicated Stasi officer Gerd Wiesler begins spying on a famous playwright and his actress-lover Christa-Maria. Wiesler becomes unexpectedly sympathetic to the couple, and faces conflicting loyalties when his superior takes a liking to Christa-Maria. | I58: Won 1 Oscar. Another 79 wins & 27 nominations. | J58: Sony Pictures Classics | K58: 87.0 | L58: 46120 | M58: 84.0 | N58: 425676 | O58: 89.0 | P58: 85.0 | Q58: 91 | R58: 92.0 | S58: 131607.0 | T58: 86 | U58: 151084.0 | V58: 91.0 | W58: itunes, amzvid | X58: https://www.rottentomatoes.com/m/the_lives_of_others | Y58: tt0405094 | Z58: 87.83
A59: 58 | B59: The Best Years of Our Lives | C59: 1946 | D59: Drama, Romance, War | E59: William Wyler | F59: Dana Andrews, Fredric March, Harold Russell, Teresa Wright | G59: en | H59: It's the hope that sustains the spirit of every GI: the dream of the day when he will finally return home. For three WWII veterans, the day has arrived. But for each man, the dream is about to become a nightmare. | I59: Won 7 Oscars. Another 14 wins & 1 nomination. | J59: RKO Radio Pictures | K59: 87.0 | L59: 46030 | M59: 81.0 | N59: 73744 | O59: 93.0 | P59: 91.0 | Q59: 63 | R59: 89.0 | S59: 20090.0 | T59: 84 | U59: 38366.0 | V59: 89.0 | W59: prime, amzvid | X59: https://www.rottentomatoes.com/m/best_years_of_our_lives | Y59: tt0036868 | Z59: 87.83
A60: 59 | B60: The Shop Around the Corner | C60: 1940 | D60: Comedy, Drama, Romance | E60: Ernst Lubitsch | F60: Margaret Sullavan, James Stewart, Frank Morgan, Joseph Schildkraut | G60: en | H60: Two employees at a gift shop can barely stand one another, without realising that they are falling in love through the post as each other's anonymous pen pal. | I60: 1 win. | J60: MGM | K60: 87.0 | L60: 8.0 | M60: 80.0 | N60: 41339 | O60: 96.0 | P60: 90.0 | Q60: 51 | R60: 88.0 | S60: 30945.0 | T60: 84 | U60: 68741.0 | V60: 89.0 | W60: itunes, amzvid, hbm | X60: https://www.rottentomatoes.com/m/shop_around_the_corner/ | Y60: tt0033045 | Z60: 87.83
A61: 60 | B61: There Will Be Blood | C61: 2007 | D61: Drama | E61: Paul Thomas Anderson | F61: Daniel Day-Lewis, Paul Dano, Kevin J. O'Connor, Ciar√°n Hinds | G61: en | H61: The story of Daniel Plainview, and his journey to become the most powerful oil tycoon of the 19th century. He cons and financially manipulates himself over the local landowners, gaining rights to their property, thoroughly cementing his dominance. All the while projecting a family man image, using his adopted son as a front for his violent intent. Local preacher Eli suspects Plainview‚Äôs unsavory aims, and thus begins a feud that threatens both lives. | I61: Won 2 Oscars. Another 117 wins & 101 nominations. | J61: Paramount Vantage | K61: 88.0 | L61: 46061 | M61: 82.0 | N61: 666631 | O61: 93.0 | P61: 87.0 | Q61: 166 | R61: 84.0 | S61: 462225.0 | T61: 90 | U61: 874342.0 | V61: 91.0 | W61: paramount, itunes, amzvid | X61: https://www.rottentomatoes.com/m/there_will_be_blood | Y61: tt0469494 | Z61: 87.83
A62: 61 | B62: The Seventh Seal | C62: 1957 | D62: Fantasy, Drama | E62: Ingmar Bergman | F62: Gunnar Bj√∂rnstrand, Bengt Ekerot, Nils Poppe, Max von Sydow | G62: sv | H62: When disillusioned Swedish knight Antonius Block returns home from the Crusades to find his country in the grips of the Black Death, he challenges Death to a chess match for his life. Tormented by the belief that God does not exist, Block sets off on a journey, meeting up with traveling players Jof and his wife, Mia, and becoming determined to evade Death long enough to commit one redemptive act while he still lives. | I62: 7 wins & 1 nomination. | J62: Janus Films | K62: 87.0 | L62: 46030 | M62: 81.0 | N62: 206854 | O62: 88.0 | P62: 91.0 | Q62: 57 | R62: 90.0 | S62: 132192.0 | T62: 86 | U62: 297436.0 | V62: 90.0 | W62: itunes, amzvid, hbm | X62: https://www.rottentomatoes.com/m/seventh_seal | Y62: tt0050976 | Z62: 87.67
A63: 62 | B63: The Lord of the Rings: The Two Towers | C63: 2002 | D63: Adventure, Fantasy, Action | E63: Peter Jackson | F63: Elijah Wood, Ian McKellen, Viggo Mortensen, Sean Astin | G63: en | H63: Frodo Baggins and the other members of the Fellowship continue on their sacred quest to destroy the One Ring--but on separate paths. Their destinies lie at two towers--Orthanc Tower in Isengard, where the corrupt wizard Saruman awaits, and Sauron's fortress at Barad-dur, deep within the dark lands of Mordor. Frodo and Sam are trekking to Mordor to destroy the One Ring of Power while Gimli, Legolas and Aragorn search for the orc-captured Merry and Pippin. All along, nefarious wizard Saruman awaits the Fellowship members at the Orthanc Tower in Isengard. | I63: Won 2 Oscars. Another 103 wins & 100 nominations. | J63: New Line Cinema | K63: 87.0 | L63: 46242 | M63: 88.0 | N63: 1861078 | O63: 87.0 | P63: 86.0 | Q63: 140 | R63: 92.0 | S63: 1379232.0 | T63: 88 | U63: 1454840.0 | V63: 85.0 | W63: hbo, itunes, amzvid, hbm | X63: https://www.rottentomatoes.com/m/the_lord_of_the_rings_the_two_towers/ | Y63: tt0167261 | Z63: 87.67
A64: 63 | B64: Do the Right Thing | C64: 1989 | D64: Drama | E64: Spike Lee | F64: Danny Aiello, Spike Lee, Ossie Davis, Richard Edson | G64: en
A67: Set in Bedford-Stuyvesant | B67: Brooklyn | C67: New York | D67: over one of the hottest days of the year | E67: a neighborhood resident Buggin‚Äô Out becomes agitated by the exhibition of Italian actors displayed on a Pizzeria wall. Buggin‚Äô Out thinks that a Pizza place in a predominantly black area should feature black actors | F67: but Salvatore ""Sal"" Fragione thinks not. The result is a heated and dramatic playout of racial hatred in 1980s New York." | G67: Nominated for 2 Oscars. Another 15 wins & 8 nominations. | H67: Universal Pictures | I67: 88.0 | J67: 8.0 | K67: 80.0 | L67: 117516 | M67: 93.0 | N67: 92.0 | O67: 82 | P67: 86.0 | Q67: 177459.0 | R67: 88 | S67: 384341.0 | T67: 86.0 | U67: prime, itunes, amzvid | V67: https://www.rottentomatoes.com/m/do_the_right_thing/ | W67: tt0097216 | X67: 87.5
A68: 64 | B68: Amadeus | C68: 1984 | D68: History, Music, Drama | E68: Milo≈° Forman | F68: F. Murray Abraham, Tom Hulce, Elizabeth Berridge, Simon Callow | G68: en | H68: Disciplined Italian composer Antonio Salieri becomes consumed by jealousy and resentment towards the hedonistic and remarkably talented young Viennese composer Wolfgang Amadeus Mozart. | I68: Won 8 Oscars. Another 34 wins & 13 nominations. | J68: Warner Bros. Pictures | K68: 87.0 | L68: 46120 | M68: 84.0 | N68: 446044 | O68: 87.0 | P68: 89.0 | Q68: 85 | R68: 91.0 | S68: 240893.0 | T68: 86 | U68: 361671.0 | V68: 88.0 | W68: itunes, amzvid | X68: https://www.rottentomatoes.com/m/amadeus | Y68: tt0086879 | Z68: 87.5
A69: 65 | B69: Eternal Sunshine of the Spotless Mind | C69: 2004 | D69: Science Fiction, Drama, Romance | E69: Michel Gondry | F69: Jim Carrey, Kate Winslet, Kirsten Dunst, Mark Ruffalo | G69: en | H69: Joel Barish, heartbroken that his girlfriend underwent a procedure to erase him from her memory, decides to do the same. However, as he watches his memories of her fade away, he realises that he still loves her, and may be too late to correct his mistake. | I69: Won 1 Oscar. Another 71 wins & 68 nominations. | J69: Focus Features | K69: 87.0 | L69: 46089 | M69: 83.0 | N69: 1129606 | O69: 89.0 | P69: 86.0 | Q69: 165 | R69: 90.0 | S69: 1168654.0 | T69: 84 | U69: 2359950.0 | V69: 93.0 | W69: itunes, amzvid | Y69: tt0338013 | Z69: 87.5
A70: 66 | B70: The Night of the Hunter | C70: 1955 | D70: Crime, Drama, Thriller | E70: Charles Laughton | F70: Robert Mitchum, Billy Chapin, Sally Jane Bruce, Shelley Winters | G70: en | H70: In Depression-era West Virginia, a serial-killing preacher hunts two young children who know the whereabouts of a stash of money. | I70: 1 win. | J70: United Artists | K70: 87.0 | L70: 8.0 | M70: 80.0 | N70: 102071 | O70: 97.0 | P70: 93.0 | Q70: 82 | R70: 87.0 | S70: 72731.0 | T70: 86 | U70: 168419.0 | V70: 82.0 | W70: itunes, amzvid | X70: https://www.rottentomatoes.com/m/night_of_the_hunter | Y70: tt0048424 | Z70: 87.5
A71: 67 | B71: Ratatouille | C71: 2007 | D71: Animation, Comedy, Family, Fantasy | E71: Brad Bird | F71: Patton Oswalt, Ian Holm, Lou Romano, Brian Dennehy | G71: en | H71: Remy, a resident of Paris, appreciates good food and has quite a sophisticated palate. He would love to become a chef so he can create and enjoy culinary masterpieces to his heart's delight. The only problem is, Remy is a rat. When he winds up in the sewer beneath one of Paris' finest restaurants, the rodent gourmet finds himself ideally placed to realize his dream. | I71: Won 1 Oscar. Another 65 wins & 37 nominations. | J71: Disney/Pixar | K71: 87.0 | L71: 46030 | M71: 81.0 | N71: 877175 | O71: 96.0 | P71: 88.0 | Q71: 152 | R71: 84.0 | S71: 1516553.0 | T71: 84 | U71: 2402281.0 | V71: 91.0 | W71: disney, itunes, amzvid | X71: https://www.rottentomatoes.com/m/ratatouille/ | Y71: tt0382932 | Z71: 87.33
A72: 68 | B72: Past Lives | C72: 2023 | D72: Drama, Romance | E72: Celine Song | F72: Greta Lee, Teo Yoo, John Magaro, Moon Seung-ah | G72: en | H72: Nora and Hae Sung, two childhood friends, are reunited in New York for one fateful week as they confront notions of destiny, love, and the choices that make a life. | K72: 87.0 | L72: 46241 | M72: 78.0 | N72: 148063 | O72: 94.0 | P72: 92.0 | Q72: 181 | S72: 422095.0 | T72: 84 | U72: 1258872.0 | V72: 88.0 | X72: https://www.rottentomatoes.com/m/past_lives | Y72: tt13238346 | Z72: 87.2
A73: 69 | B73: The Departed | C73: 2006 | D73: Drama, Thriller, Crime | E73: Martin Scorsese | F73: Leonardo DiCaprio, Matt Damon, Jack Nicholson, Mark Wahlberg | G73: en | H73: To take down South Boston's Irish Mafia, the police send in one of their own to infiltrate the underworld, not realizing the syndicate has done likewise. While an undercover cop curries favor with the mob kingpin, a career criminal rises through the police ranks. But both sides soon discover there's a mole among them. | I73: Won 4 Oscars. Another 102 wins & 88 nominations. | J73: Warner Bros. Pictures | K73: 86.0 | L73: 46150 | M73: 85.0 | N73: 1478709 | O73: 85.0 | P73: 84.0 | Q73: 172 | R73: 91.0 | S73: 853886.0 | T73: 86 | U73: 1082954.0 | V73: 92.0 | W73: itunes, amzvid, hbm | X73: https://www.rottentomatoes.com/m/departed | Y73: tt0407887 | Z73: 87.17
A74: 70 | B74: Chinatown | C74: 1974 | D74: Crime, Drama, Mystery, Thriller | E74: Roman Polanski | F74: Jack Nicholson, Faye Dunaway, John Huston, Perry Lopez | G74: en | H74: Private eye Jake Gittes lives off of the murky moral climate of sunbaked, pre-World War II Southern California. Hired by a beautiful socialite to investigate her husband's extra-marital affair, Gittes is swept into a maelstrom of double dealings and deadly deceits, uncovering a web of personal and political scandals that come crashing together. | I74: Won 1 Oscar. Another 21 wins & 22 nominations. | J74: Paramount Pictures | K74: 87.0 | L74: 46030 | M74: 81.0 | N74: 362976 | O74: 92.0 | P74: 94.0 | Q74: 63 | R74: 89.0 | S74: 176581.0 | T74: 86 | U74: 373349.0 | V74: 81.0 | W74: paramount, itunes, amzvid, hbm | Y74: tt0071315 | Z74: 87.17
A75: 71 | B75: Paths of Glory | C75: 1957 | D75: War, Drama, History | E75: Stanley Kubrick | F75: Kirk Douglas, Ralph Meeker, Adolphe Menjou, George Macready | G75: en | H75: A commanding officer defends three scapegoats on trial for a failed offensive that occurred within the French Army in 1916. | I75: Nominated for 1 BAFTA Film Award. Another 4 wins & 2 nominations. | J75: United Artists | K75: 86.0 | L75: 46120 | M75: 84.0 | N75: 224612 | O75: 90.0 | P75: 90.0 | Q75: 68 | R75: 92.0 | S75: 99118.0 | T75: 88 | U75: 226166.0 | V75: 79.0 | W75: itunes, amzvid | X75: https://www.rottentomatoes.com/m/paths_of_glory | Y75: tt0050825 | Z75: 87.17
A76: 72 | B76: Monty Python and the Holy Grail | C76: 1975 | D76: Adventure, Comedy, Fantasy | E76: Terry Jones, Terry Gilliam | F76: Graham Chapman, John Cleese, Eric Idle, Terry Gilliam | G76: en | H76: Pythons surrealist comedic take on the legend of King Arthur, the mythical King of the Britons, and his quest for the Holy Grail. Along with his newly recruited Knights of the Round Table: Sir Lancelot the Brave, Sir Robin the Not-So-Brave, Sir Bedevere the Wise, and Sir Galahad the Pure ‚Äì they journey through perilous horrors, including a delusional Black Knight, the Knights who say ‚ÄòNee‚Äô, a house full of virgins, a castle of rather rude Frenchmen. | I76: 1 win & 2 nominations. | J76: Almi Cinema 5 | K76: 86.0 | L76: 46061 | M76: 82.0 | N76: 584895 | O76: 91.0 | P76: 87.0 | Q76: 60 | R76: 90.0 | S76: 602159.0 | T76: 82 | U76: 515943.0 | V76: 91.0 | W76: britbox, prime, peacock, itunes, amzvid | X76: https://www.rottentomatoes.com/m/monty_python_and_the_holy_grail | Y76: tt0071853 | Z76: 87.17
A77: 73 | B77: My Neighbor Totoro | C77: 1988 | D77: Fantasy, Animation, Family | E77: Hayao Miyazaki | F77: Noriko Hidaka, Chika Sakamoto, Hitoshi Takagi, Shigesato Itoi | G77: ja | H77: Two sisters move to the country with their father in order to be closer to their hospitalized mother, and discover the surrounding trees are inhabited by Totoros, magical spirits of the forest. When the youngest runs away from home, the older sister seeks help from the spirits to find her. | I77: 5 wins & 1 nomination. | J77: Tokuma Shoten | K77: 86.0 | L77: 46030 | M77: 81.0 | N77: 403332 | O77: 87.0 | P77: 86.0 | Q77: 54 | R77: 90.0 | S77: 503212.0 | T77: 84 | U77: 1326860.0 | V77: 94.0 | W77: itunes, amzvid, hbm | X77: https://www.rottentomatoes.com/m/my_neighbor_totoro | Y77: tt0096283 | Z77: 87.0
A78: 74 | B78: L.A. Confidential | C78: 1997 | D78: Crime, Mystery, Thriller, Drama | E78: Curtis Hanson | F78: Guy Pearce, Russell Crowe, Kevin Spacey, Kim Basinger | G78: en | H78: Three detectives in the corrupt and brutal L.A. police force of the 1950s use differing methods to uncover a conspiracy behind the shotgun slayings of the patrons at an all-night diner. | I78: Won 2 Oscars. Another 95 wins & 62 nominations. | J78: Warner Bros. Pictures | K78: 86.0 | L78: 46061 | M78: 82.0 | N78: 638085 | O78: 91.0 | P78: 90.0 | Q78: 96 | R78: 90.0 | S78: 205235.0 | T78: 82 | U78: 312718.0 | V78: 87.0 | W78: hulu, disney, prime | X78: https://www.rottentomatoes.com/m/la_confidential | Y78: tt0119488 | Z78: 87.0
A79: 75 | B79: The Lion King | C79: 1994 | D79: Family, Animation, Drama | E79: Roger Allers, Rob Minkoff | F79: Matthew Broderick, Moira Kelly, Nathan Lane, Ernie Sabella | G79: en | H79: Young lion prince Simba, eager to one day become king of the Pride Lands, grows up under the watchful eye of his father Mufasa; all the while his villainous uncle Scar conspires to take the throne for himself. Amid betrayal and tragedy, Simba must confront his past and find his rightful place in the Circle of Life. | I79: Won 2 Oscars. Another 28 wins & 25 nominations. | J79: Buena Vista | K79: 86.0 | L79: 46150 | M79: 85.0 | N79: 1194520 | O79: 88.0 | P79: 86.0 | Q79: 115 | R79: 90.0 | S79: 1332919.0 | T79: 84 | U79: 1460091.0 | V79: 89.0 | W79: disney, itunes, amzvid | X79: https://www.rottentomatoes.com/m/the_lion_king | Y79: tt0110357 | Z79: 87.0
A80: 76 | B80: Hamilton | C80: 2020 | D80: History, Drama | E80: Thomas Kail | F80: Lin-Manuel Miranda, Leslie Odom Jr., Ren√©e Elise Goldsberry, Phillipa Soo | G80: en | H80: Presenting the tale of American founding father Alexander Hamilton, this filmed version of the original Broadway smash hit is the story of America then, told by America now. | K80: 87.0 | L80: 46089 | M80: 83.0 | N80: 126439 | O80: 88.0 | P80: 91.0 | Q80: 102 | R80: 88.0 | S80: 142644.0 | T80: 84 | U80: 423181.0 | V80: 87.0 | X80: https://www.rottentomatoes.com/m/hamilton_2020 | Y80: tt8503618 | Z80: 86.83
A81: 77 | B81: Cinema Paradiso | C81: 1988 | D81: Drama, Romance | E81: Giuseppe Tornatore | F81: Philippe Noiret, Jacques Perrin, Marco Leonardi, Salvatore Cascio | G81: it | H81: A filmmaker recalls his childhood, when he fell in love with the movies at his village's theater and formed a deep friendship with the theater's projectionist. | I81: Won 1 Oscar. Another 20 wins & 23 nominations. | J81: Miramax Films | K81: 86.0 | L81: 46150 | M81: 85.0 | N81: 299114 | O81: 80.0 | P81: 81.0 | Q81: 61 | R81: 93.0 | S81: 156145.0 | T81: 90 | U81: 336814.0 | V81: 92.0 | W81: itunes, amzvid | X81: https://www.rottentomatoes.com/m/cinema_paradiso | Y81: tt0095765 | Z81: 86.83
A82: 78 | B82: City of God | C82: 2002 | D82: Drama, Crime | E82: Fernando Meirelles | F82: Alexandre Rodrigues, Leandro Firmino, Phellipe Haagensen, Douglas Silva | G82: pt | H82: In the poverty-stricken favelas of Rio de Janeiro in the 1970s, two young men choose different paths. Rocket is a budding photographer who documents the increasing drug-related violence of his neighborhood, while Jos√© ‚ÄúZ√©‚Äù Pequeno is an ambitious drug dealer diving into a dangerous life of crime. | I82: Nominated for 4 Oscars. Another 70 wins & 29 nominations. | J82: Miramax Films | K82: 86.0 | L82: 46181 | M82: 86.0 | N82: 832918 | O82: 79.0 | P82: 82.0 | Q82: 110 | R82: 93.0 | S82: 417654.0 | T82: 90 | U82: 747463.0 | V82: 91.0 | W82: itunes, amzvid | X82: https://www.rottentomatoes.com/m/city_of_god | Y82: tt0317248 | Z82: 86.83
A83: 79 | B83: Wolfwalkers | C83: 2020 | D83: Animation, Family, Adventure, Fantasy | E83: Tomm Moore, Ross Stewart | F83: Honor Kneafsey, Eva Whittaker, Sean Bean, Simon McBurney | G83: en | H83: In a time of superstition and magic, when wolves are seen as demonic and nature an evil to be tamed, a young apprentice hunter comes to Ireland with her father to wipe out the last pack. But when she saves a wild native girl, their friendship leads her to discover the world of the Wolfwalkers and transform her into the very thing her father is tasked to destroy. | K83: 85.0 | L83: 8.0 | M83: 80.0 | N83: 41605 | O83: 87.0 | P83: 87.0 | Q83: 109 | R83: 95.0 | S83: 45817.0 | T83: 84 | U83: 135079.0 | V83: 88.0 | W83: apple | Y83: tt5198068 | Z83: 86.83
A84: 80 | B84: The Bridge on the River Kwai | C84: 1957 | D84: Drama, History, War | E84: David Lean | F84: William Holden, Alec Guinness, Jack Hawkins, Sessue Hayakawa | G84: en | H84: The classic story of English POWs in Burma forced to build a bridge to aid the war effort of their Japanese captors. British and American intelligence officers conspire to blow up the structure, but Col. Nicholson, the commander who supervised the bridge's construction, has acquired a sense of pride in his creation and tries to foil their plans. | I84: Won 7 Oscars. Another 23 wins & 7 nominations. | J84: Columbia Pictures | K84: 87.0 | L84: 46030 | M84: 81.0 | N84: 240528 | O84: 88.0 | P84: 93.0 | Q84: 64 | R84: 89.0 | S84: 67210.0 | T84: 84 | U84: 91805.0 | V84: 86.0 | W84: itunes, amzvid, hbm | X84: https://www.rottentomatoes.com/m/bridge_on_the_river_kwai | Y84: tt0050212 | Z84: 86.83
A85: 81 | B85: I'm Still Here | C85: 2024 | D85: Drama, History | E85: Walter Salles | F85: Fernanda Torres, Selton Mello, Valentina Herszage, B√°rbara Luz | G85: pt | H85: In 1971, military dictatorship in Brazil reaches its height. The Paiva family ‚Äî Rubens, Eunice, and their five children ‚Äî live in a beachside house in Rio, open to all their friends. One day, Rubens is taken for questioning and does not return. | K85: 87.0 | L85: 46120 | M85: 84.0 | N85: 94661 | O85: 85.0 | P85: 84.0 | Q85: 106 | T85: 86 | U85: 526291.0 | V85: 95.0 | W85: netflix | X85: https://www.rottentomatoes.com/m/im_still_here_2024 | Y85: tt14961016 | Z85: 86.8
A86: 82 | B86: It Happened One Night | C86: 1934 | D86: Comedy, Romance | E86: Frank Capra | F86: Clark Gable, Claudette Colbert, Walter Connolly, Roscoe Karns | G86: en | H86: A runaway heiress makes a deal with the rogue reporter trailing her but the mismatched pair end up stuck with each other when their bus leaves them behind. | I86: Won 5 Oscars. Another 5 wins & 1 nomination. | J86: Sony Pictures Home Entertainment | K86: 86.0 | L86: 46030 | M86: 81.0 | N86: 116269 | O86: 87.0 | P86: 90.0 | Q86: 72 | R86: 89.0 | S86: 56458.0 | T86: 84 | U86: 101589.0 | V86: 89.0 | W86: itunes, amzvid | X86: https://www.rottentomatoes.com/m/it_happened_one_night/ | Y86: tt0025316 | Z86: 86.67
A87: 83 | B87: Beauty and the Beast | C87: 1991 | D87: Romance, Family, Animation, Fantasy | E87: Gary Trousdale, Kirk Wise | F87: Paige O'Hara, Robby Benson, Richard White, Jerry Orbach | G87: en | H87: Follow the adventures of Belle, a bright young woman who finds herself in the castle of a prince who's been turned into a mysterious beast. With the help of the castle's enchanted staff, Belle soon learns the most important lesson of all -- that true beauty comes from within. | I87: Won 2 Oscars. Another 22 wins & 20 nominations. | J87: Buena Vista | K87: 86.0 | L87: 8.0 | M87: 80.0 | N87: 491091 | O87: 95.0 | P87: 89.0 | Q87: 102 | R87: 88.0 | S87: 679535.0 | T87: 78 | U87: 640107.0 | V87: 90.0 | W87: disney, itunes, amzvid | X87: https://www.rottentomatoes.com/m/beauty_and_the_beast_1991/ | Y87: tt0101414 | Z87: 86.67
A88: 84 | B88: Spider-Man: Into the Spider-Verse | C88: 2018 | D88: Animation, Action, Adventure, Science Fiction | E88: Bob Persichetti, Peter Ramsey, Rodney Rothman | F88: Shameik Moore, Jake Johnson, Hailee Steinfeld, Mahershala Ali | G88: en | H88: Struggling to find his place in the world while juggling school and family, Brooklyn teenager Miles Morales is unexpectedly bitten by a radioactive spider and develops unfathomable powers just like the one and only Spider-Man. While wrestling with the implications of his new abilities, Miles discovers a super collider created by the madman Wilson "Kingpin" Fisk, causing others from across the Spider-Verse to be inadvertently transported to his dimension. | K88: 86.0 | L88: 46120 | M88: 84.0 | N88: 723333 | O88: 87.0 | P88: 88.0 | Q88: 242 | R88: 90.0 | S88: 1068834.0 | T88: 88 | U88: 3153094.0 | V88: 83.0 | W88: netflix, itunes, amzvid | X88: https://www.rottentomatoes.com/m/spider_man_into_the_spider_verse/ | Y88: tt4633694 | Z88: 86.67
A89: 85 | B89: 8¬Ω | C89: 1963 | D89: Drama | E89: Federico Fellini | F89: Marcello Mastroianni, Anouk Aim√©e, Sandra Milo, Claudia Cardinale | G89: it | H89: Guido Anselmi, a film director, finds himself creatively barren at the peak of his career. Urged by his doctors to rest, Anselmi heads for a luxurious resort, but a sorry group gathers‚Äîhis producer, staff, actors, wife, mistress, and relatives‚Äîeach one begging him to get on with the show. In retreat from their dependency, he fantasizes about past women and dreams of his childhood. | I89: Won 2 Oscars. Another 16 wins & 8 nominations. | J89: Cinerez | K89: 86.0 | L89: 8.0 | M89: 80.0 | N89: 128719 | O89: 93.0 | P89: 87.0 | Q89: 53 | R89: 89.0 | S89: 95771.0 | T89: 86 | U89: 196861.0 | V89: 85.0 | W89: itunes, amzvid, hbm | X89: https://www.rottentomatoes.com/m/8_12 | Y89: tt0056801 | Z89: 86.67
A90: 86 | B90: Spider-Man: Across the Spider-Verse | C90: 2023 | D90: Animation, Action, Adventure, Science Fiction | E90: Kemp Powers, Justin K. Thompson, Joaquim Dos Santos | F90: Shameik Moore, Hailee Steinfeld, Brian Tyree Henry, Luna Lauren Velez | G90: en | H90: After reuniting with Gwen Stacy, Brooklyn‚Äôs full-time, friendly neighborhood Spider-Man is catapulted across the Multiverse, where he encounters the Spider Society, a team of Spider-People charged with protecting the Multiverse‚Äôs very existence. But when the heroes clash on how to handle a new threat, Miles finds himself pitted against the other Spiders and must set out on his own to save those he loves most. | K90: 87.0 | L90: 46150 | M90: 85.0 | N90: 441825 | O90: 86.0 | P90: 86.0 | Q90: 222 | S90: 838214.0 | T90: 88 | U90: 2432408.0 | V90: 88.0 | W90: disney | X90: https://www.rottentomatoes.com/m/spider_man_across_the_spider_verse | Y90: tt9362722 | Z90: 86.6
A91: 87 | B91: The Wild Robot | C91: 2024 | D91: Animation, Science Fiction, Family | E91: Chris Sanders | F91: Lupita Nyong'o, Pedro Pascal, Kit Connor, Bill Nighy | G91: en | H91: After a shipwreck, an intelligent robot called Roz is stranded on an uninhabited island. To survive the harsh environment, Roz bonds with the island's animals and cares for an orphaned baby goose. | K91: 87.0 | L91: 46061 | M91: 82.0 | N91: 151761 | O91: 85.0 | P91: 84.0 | Q91: 143 | T91: 84 | U91: 807351.0 | V91: 98.0 | W91: peacock | X91: https://www.rottentomatoes.com/m/the_wild_robot | Y91: tt29623480 | Z91: 86.6
A92: 88 | B92: Gone with the Wind | C92: 1939 | D92: Drama, War, Romance | E92: Victor Fleming | F92: Vivien Leigh, Clark Gable, Olivia de Havilland, Leslie Howard | G92: en | H92: The spoiled daughter of a Georgia plantation owner conducts a tumultuous romance with a cynical profiteer during the American Civil War and Reconstruction Era. | I92: Won 8 Oscars. Another 11 wins & 6 nominations. | J92: Loew's Inc. | K92: 86.0 | L92: 46061 | M92: 82.0 | N92: 344610 | O92: 97.0 | P92: 90.0 | Q92: 66 | R92: 88.0 | S92: 259241.0 | T92: 78 | U92: 189395.0 | V92: 84.0 | W92: hbo, itunes, amzvid, hbm | X92: https://www.rottentomatoes.com/m/gone_with_the_wind | Y92: tt0031381 | Z92: 86.5
A93: 89 | B93: The Wild Bunch | C93: 1969 | D93: Western | E93: Sam Peckinpah | F93: William Holden, Ernest Borgnine, Robert Ryan, Jaime S√°nchez | G93: en | H93: An aging group of outlaws look for one last big score as the "traditional" American West is disappearing around them. | I93: Nominated for 2 Oscars. Another 6 wins & 3 nominations. | J93: Warner Bros. Pictures | K93: 86.0 | L93: 46272 | M93: 79.0 | N93: 92654 | O93: 98.0 | P93: 91.0 | Q93: 54 | R93: 87.0 | S93: 43809.0 | T93: 82 | U93: 62739.0 | V93: 82.0 | W93: itunes, amzvid | X93: https://www.rottentomatoes.com/m/1059489_wild_bunch | Y93: tt0065214 | Z93: 86.5
A94: 90 | B94: In the Mood for Love | C94: 2000 | D94: Drama, Romance | E94: Wong Kar-wai | F94: Tony Leung, Maggie Cheung Man-Yuk, Rebecca Pan, Kelly Lai Chen | G94: cn | H94: In 1962 Hong Kong, two neighbors form a strong bond after both suspect extramarital activities of their spouses. | I94: Nominated for 1 BAFTA Film Award. Another 43 wins & 38 nominations. | J94: USA Films | K94: 85.0 | L94: 46030 | M94: 81.0 | N94: 175775 | O94: 87.0 | P94: 82.0 | Q94: 87 | R94: 90.0 | S94: 251393.0 | T94: 88 | U94: 645707.0 | V94: 91.0 | W94: hbm | X94: https://www.rottentomatoes.com/m/in_the_mood_for_love_2001 | Y94: tt0118694 | Z94: 86.5
A95: 91 | B95: Toy Story 3 | C95: 2010 | D95: Animation, Family, Comedy | E95: Lee Unkrich | F95: Tom Hanks, Tim Allen, Joan Cusack, Don Rickles | G95: en | H95: Woody, Buzz, and the rest of Andy's toys haven't been played with in years. With Andy about to go to college, the gang find themselves accidentally left at a nefarious day care center. The toys must band together to escape and return home to Andy. | I95: Won 2 Oscars. Another 61 wins & 81 nominations. | J95: Walt Disney Pictures | K95: 86.0 | L95: 46089 | M95: 83.0 | N95: 926157 | O95: 92.0 | P95: 90.0 | Q95: 218 | R95: 86.0 | S95: 796262.0 | T95: 80 | U95: 1171417.0 | V95: 88.0 | W95: disney, itunes, amzvid | X95: https://www.rottentomatoes.com/m/toy_story_3 | Y95: tt0435761 | Z95: 86.5
A96: 92 | B96: The Truman Show | C96: 1998 | D96: Comedy, Drama | E96: Peter Weir | F96: Jim Carrey, Laura Linney, Noah Emmerich, Natascha McElhone | G96: en | H96: Every second of every day, from the moment he was born, for the last thirty years, Truman Burbank has been the unwitting star of the longest running, most popular documentary-soap opera in history. The picture-perfect town of Seahaven that he calls home is actually a gigantic soundstage. Truman's friends and family - everyone he meets, in fact - are actors. He lives every moment under the unblinking gaze of thousands of hidden TV cameras. | I96: Nominated for 3 Oscars. Another 35 wins & 64 nominations. | J96: Paramount Pictures | K96: 86.0 | L96: 46061 | M96: 82.0 | N96: 1267347 | O96: 90.0 | P96: 86.0 | Q96: 108 | R96: 87.0 | S96: 1350393.0 | T96: 84 | U96: 2880682.0 | V96: 90.0 | W96: paramount, itunes, amzvid, hbm | X96: https://www.rottentomatoes.com/m/truman_show | Y96: tt0120382 | Z96: 86.5
A97: 93 | B97: Fargo | C97: 1996 | D97: Crime, Drama, Thriller | E97: Joel Coen | F97: Frances McDormand, William H. Macy, Steve Buscemi, Peter Stormare | G97: en | H97: Jerry, a small-town Minnesota car salesman is bursting at the seams with debt... but he's got a plan. He's going to hire two thugs to kidnap his wife in a scheme to collect a hefty ransom from his wealthy father-in-law. It's going to be a snap and nobody's going to get hurt... until people start dying. Enter Police Chief Marge, a coffee-drinking, parka-wearing - and extremely pregnant - investigator who'll stop at nothing to get her man. And if you think her small-time investigative skills will give the crooks a run for their ransom... you betcha! | I97: Won 2 Oscars. Another 78 wins & 42 nominations. | J97: MGM | K97: 86.0 | L97: 46030 | M97: 81.0 | N97: 751771 | O97: 88.0 | P97: 88.0 | Q97: 72 | R97: 89.0 | S97: 470077.0 | T97: 84 | U97: 939939.0 | V97: 89.0 | W97: itunes, amzvid | X97: https://www.rottentomatoes.com/m/fargo/ | Y97: tt0116282 | Z97: 86.5
A98: 94 | B98: Shoplifters | C98: 2018 | D98: Drama, Crime, Thriller | E98: Hirokazu Kore-eda | F98: Lily Franky, Sakura Ando, Mayu Matsuoka, Kairi Jo | G98: ja | H98: After one of their shoplifting sessions, Osamu and his son come across a little girl in the freezing cold. At first reluctant to shelter the girl, Osamu‚Äôs wife agrees to take care of her after learning of the hardships she faces. Although the family is poor, barely making enough money to survive through petty crime, they seem to live happily together until an unforeseen incident reveals hidden secrets, testing the bonds that unite them. | K98: 86.0 | L98: 46272 | M98: 79.0 | N98: 91034 | O98: 93.0 | P98: 89.0 | Q98: 147 | R98: 88.0 | S98: 83143.0 | T98: 86 | U98: 244423.0 | V98: 84.0 | W98: itunes, amzvid | X98: https://www.rottentomatoes.com/m/shoplifters | Y98: tt8075192 | Z98: 86.5
A99: 95 | B99: No Country for Old Men | C99: 2007 | D99: Crime, Drama, Thriller | E99: Joel Coen, Ethan Coen | F99: Javier Bardem, Tommy Lee Jones, Josh Brolin, Woody Harrelson | G99: en | H99: Llewelyn Moss stumbles upon dead bodies, $2 million and a hoard of heroin in a Texas desert, but methodical killer Anton Chigurh comes looking for it, with local sheriff Ed Tom Bell hot on his trail. The roles of prey and predator blur as the violent pursuit of money and justice collide. | I99: Won 4 Oscars. Another 168 wins & 98 nominations. | J99: Miramax Films | K99: 87.0 | L99: 46061 | M99: 82.0 | N99: 1113836 | O99: 92.0 | P99: 89.0 | Q99: 206 | R99: 84.0 | S99: 743270.0 | T99: 86 | U99: 1428294.0 | V99: 85.0 | W99: prime, paramount, itunes, amzvid, hbm | X99: https://www.rottentomatoes.com/m/no_country_for_old_men | Y99: tt0477348 | Z99: 86.33
A100: 96 | B100: Aliens | C100: 1986 | D100: Action, Thriller, Science Fiction | E100: James Cameron | F100: Sigourney Weaver, Carrie Henn, Michael Biehn, Paul Reiser | G100: en | H100: Ripley, the sole survivor of the Nostromo's deadly encounter with the monstrous Alien, returns to Earth after drifting through space in hypersleep for 57 years. Although her story is initially met with skepticism, she agrees to accompany a team of Colonial Marines back to LV-426. | I100: Won 2 Oscars. Another 16 wins & 22 nominations. | J100: 20th Century Fox Film Corporat | K100: 86.0 | L100: 46120 | M100: 84.0 | N100: 804533 | O100: 84.0 | P100: 88.0 | Q100: 99 | R100: 90.0 | S100: 516707.0 | T100: 82 | U100: 687721.0 | V100: 90.0 | W100: hbo, itunes, amzvid | X100: https://www.rottentomatoes.com/m/1000617-aliens/ | Y100: tt0090605 | Z100: 86.33
A101: 97 | B101: La Dolce Vita | C101: 1960 | D101: Comedy, Drama | E101: Federico Fellini | F101: Marcello Mastroianni, Anita Ekberg, Anouk Aim√©e, Yvonne Furneaux | G101: it | H101: Episodic journey of journalist Marcello who struggles to find his place in the world, torn between the allure of Rome's elite social scene and the stifling domesticity offered by his girlfriend, all the while searching for a way to become a serious writer. | I101: Won 1 Oscar. Another 10 wins & 12 nominations. | J101: American International Picture | K101: 86.0 | L101: 8.0 | M101: 80.0 | N101: 82147 | O101: 95.0 | P101: 92.0 | Q101: 66 | R101: 87.0 | S101: 62176.0 | T101: 86 | U101: 118064.0 | V101: 78.0 | X101: https://www.rottentomatoes.com/m/dolce_vita | Y101: tt0053779 | Z101: 86.33
A102: 98 | B102: Once Upon a Time in the West | C102: 1968 | D102: Drama, Western | E102: Sergio Leone | F102: Claudia Cardinale, Henry Fonda, Jason Robards, Charles Bronson | G102: it | H102: As the railroad builders advance unstoppably through the Arizona desert on their way to the sea, Jill arrives in the small town of Flagstone with the intention of starting a new life. | I102: 4 wins & 5 nominations. | J102: Paramount Pictures | K102: 86.0 | L102: 46150 | M102: 85.0 | N102: 365674 | O102: 82.0 | P102: 89.0 | Q102: 61 | R102: 92.0 | S102: 112953.0 | T102: 88 | U102: 206571.0 | V102: 82.0 | W102: paramount, itunes, amzvid | X102: https://www.rottentomatoes.com/m/once_upon_a_time_in_the_west | Y102: tt0064116 | Z102: 86.33
...

Sheet Pivot_analysis
A3: Row Labels | B3: Average of IMDb_10 | C3: Count of IMDb_10 | F3: Row Labels | G3: Count of Title
A4: Action, Adventure | B4: 7.7 | C4: 1 | F4: Martin Scorsese | G4: 8
A5: Action, Adventure, Animation, Family | B5: 8 | C5: 1 | F5: Steven Spielberg | G5: 8
A6: Action, Adventure, Drama | B6: 7.8 | C6: 1 | F6: Stanley Kubrick | G6: 7
A7: Action, Adventure, Science Fiction | B7: 7.675 | C7: 4 | F7: Alfred Hitchcock | G7: 7
A8: Action, Adventure, Thriller | B8: 7.8 | C8: 1 | F8: Hayao Miyazaki | G8: 7
A9: Action, Crime | B9: 7.85 | C9: 2 | F9: Wes Anderson | G9: 6
A10: Action, Crime, Thriller | B10: 7.8 | C10: 3 | F10: Quentin Tarantino | G10: 6
A11: Action, Drama | B11: 8.4 | C11: 2 | F11: Alfonso Cuarón | G11: 5
A12: Action, Drama, History | B12: 8.2 | C12: 1 | F12: Christopher Nolan | G12: 5
A13: Action, Drama, Mystery, Thriller | B13: 8 | C13: 1 | F13: Denis Villeneuve | G13: 5
A14: Action, Drama, Thriller | B14: 7.8 | C14: 1 | F14: Grand Total | G14: 64
A15: Action, Drama, War | B15: 7.8 | C15: 1
A16: Action, Science Fiction | B16: 8.7 | C16: 1
A17: Action, Science Fiction, Adventure | B17: 8.8 | C17: 1
A18: Action, Thriller | B18: 8.2 | C18: 1
A19: Action, Thriller, Crime | B19: 8.2 | C19: 1
A20: Action, Thriller, Drama | B20: 7.8 | C20: 1
A21: Action, Thriller, Science Fiction | B21: 8.3666667 | C21: 3
A22: Adventure, Action | B22: 8.4 | C22: 1
A23: Adventure, Action, Science Fiction | B23: 8.65 | C23: 2
A24: Adventure, Action, Thriller | B24: 7.85 | C24: 2
A25: Adventure, Animation, Comedy, Family | B25: 7.9 | C25: 1
A26: Adventure, Comedy, Animation | B26: 7.8 | C26: 1
... A232: Grand Total | B232: 7.9694878 | C232: 449

Sheet  Clean_data
A1: Rank | B1: Title | C1: Year | D1: Genre | E1: Director | F1: Language | G1: Awards | H1: Production | I1: Flickmetrix_Score | J1: IMDb_10 | K1: IMDb_100 | L1: IMDb_Votes | M1: Metacritic | N1: Critic_Rating_RT | O1: Critic_Reviews | P1: Audience_Rating | Q1: Audience_Reviews | R1: Letterboxd | S1: Letterboxd_Votes | T1: Google_Score | U1: Streaming_On | V1: Custom_Score | W1: Gap_Score | X1: Decade
A2: 1 | B2: The Godfather | C2: 1972 | D2: Drama, Crime | E2: Francis Ford Coppola | F2: en | G2: Won 3 Oscars. Another 30 wins & 19 nominations. | H2: Paramount Pictures | I2: 93 | J2: 9.2 | K2: 92 | L2: 2108796 | M2: 100 | N2: 96 | O2: 104 | P2: 95 | Q2: 1087289 | R2: 90 | S2: 1789555 | T2: 90 | U2: paramount, itunes, amzvid | V2: 93.83 | W2: =Top_500_Movies_Ranked_by_Combined_Critics_and_Audience_Scores[[#This Row],[Critic_Rating_RT]]-Top_500_Movies_Ranked_by_Combined_Critics_and_Audience_Scores[[#This Row],[Audience_Rating]] -> 1 | X2: =FLOOR(Top_500_Movies_Ranked_by_Combined_Critics_and_Audience_Scores[[#This Row],[Year]],10) -> 1970
A3: 2 | B3: Seven Samurai | C3: 1954 | D3: Action, Drama | E3: Akira Kurosawa | F3: ja | G3: Nominated for 2 Oscars. Another 6 wins & 5 nominations. | H3: Columbia Pictures | I3: 93 | J3: 8.6 | K3: 86 | L3: 381712 | M3: 98 | N3: 97 | O3: 68 | P3: 94 | Q3: 167123 | R3: 92 | S3: 318537 | T3: 93 | U3: hbo, itunes, amzvid, hbm | V3: 93.33 | W3: =Top_500_Movies_Ranked_by_Combined_Critics_and_Audience_Scores[[#This Row],[Critic_Rating_RT]]-Top_500_Movies_Ranked_by_Combined_Critics_and_Audience_Scores[[#This Row],[Audience_Rating]] -> 3 | X3: =FLOOR(Top_500_Movies_Ranked_by_Combined_Critics_and_Audience_Scores[[#This Row],[Year]],10) -> 1950
A4: 3 | B4: 12 Angry Men | C4: 1957 | D4: Drama | E4: Sidney Lumet | F4: en | G4: Nominated for 3 Oscars. Another 16 wins & 8 nominations. | H4: Criterion Collection | I4: 92 | J4: 9 | K4: 90 | L4: 917215 | M4: 97 | N4: 93 | O4: 58 | P4: 94 | Q4: 376697 | R4: 92 | S4: 917590 | T4: 91 | U4: itunes, amzvid | V4: 92.83 | W4: =Top_500_Movies_Ranked_by_Combined_Critics_and_Audience_Scores[[#This Row],[Critic_Rating_RT]]-Top_500_Movies_Ranked_by_Combined_Critics_and_Audience_Scores[[#This Row],[Audience_Rating]] -> -1 | X4: =FLOOR(Top_500_Movies_Ranked_by_Combined_Critics_and_Audience_Scores[[#This Row],[Year]],10) -> 1950
A5: 4 | B5: Schindler's List | C5: 1993 | D5: Drama, History, War | E5: Steven Spielberg | F5: en | G5: Won 7 Oscars. Another 74 wins & 26 nominations. | H5: Universal Pictures | I5: 92 | J5: 9 | K5: 90 | L5: 1512905 | M5: 95 | N5: 93 | O5: 82 | P5: 94 | Q5: 601555 | R5: 90 | S5: 978054 | T5: 93 | U5: itunes, amzvid | V5: 92.5 | W5: =Top_500_Movies_Ranked_by_Combined_Critics_and_Audience_Scores[[#This Row],[Critic_Rating_RT]]-Top_500_Movies_Ranked_by_Combined_Critics_and_Audience_Scores[[#This Row],[Audience_Rating]] -> -1 | X5: =FLOOR(Top_500_Movies_Ranked_by_Combined_Critics_and_Audience_Scores[[#This Row],[Year]],10) -> 1990
A6: 5 | B6: The Godfather: Part II | C6: 1974 | D6: Drama, Crime | E6: Francis Ford Coppola | F6: en | G6: Won 6 Oscars. Another 13 wins & 16 nominations. | H6: Paramount Pictures | I6: 92 | J6: 9 | K6: 90 | L6: 1420179 | M6: 90 | N6: 95 | O6: 80 | P6: 94 | Q6: 586600 | R6: 92 | S6: 934120 | T6: 89 | U6: paramount, itunes, amzvid | V6: 91.67 | W6: =Top_500_Movies_Ranked_by_Combined_Critics_and_Audience_Scores[[#This Row],[Critic_Rating_RT]]-Top_500_Movies_Ranked_by_Combined_Critics_and_Audience_Scores[[#This Row],[Audience_Rating]] -> 1 | X6: =FLOOR(Top_500_Movies_Ranked_by_Combined_Critics_and_Audience_Scores[[#This Row],[Year]],10) -> 1970
A7: 6 | B7: Rear Window | C7: 1954 | D7: Thriller, Mystery | E7: Alfred Hitchcock | F7: en | G7: Nominated for 4 Oscars. Another 7 wins & 7 nominations. | H7: Paramount Pictures | I7: 91 | J7: 8.5 | K7: 85 | L7: 542959 | M7: 100 | N7: 95 | O7: 94 | P7: 92 | Q7: 303476 | R7: 88 | S7: 607614 | T7: 90 | U7: itunes, amzvid | V7: 91.67 | W7: =Top_500_Movies_Ranked_by_Combined_Critics_and_Audience_Scores[[#This Row],[Critic_Rating_RT]]-Top_500_Movies_Ranked_by_Combined_Critics_and_Audience_Scores[[#This Row],[Audience_Rating]] -> 3 | X7: =FLOOR(Top_500_Movies_Ranked_by_Combined_Critics_and_Audience_Scores[[#This Row],[Year]],10) -> 1950
A8: 7 | B8: Pulp Fiction | C8: 1994 | D8: Thriller, Crime | E8: Quentin Tarantino | F8: en | G8: Won 1 Oscar. Another 63 wins & 47 nominations. | H8: Miramax Films | I8: 91 | J8: 8.9 | K8: 89 | L8: 2319136 | M8: 95 | N8: 94 | O8: 132 | P8: 93 | Q8: 1731042 | R8: 86 | S8: 2931535 | T8: 92 | U8: paramount, peacock, itunes, amzvid, hbm | V8: 91.5 | W8: =Top_500_Movies_Ranked_by_Combined_Critics_and_Audience_Scores[[#This Row],[Critic_Rating_RT]]-Top_500_Movies_Ranked_by_Combined_Critics_and_Audience_Scores[[#This Row],[Audience_Rating]] -> 1 | X8: =FLOOR(Top_500_Movies_Ranked_by_Combined_Critics_and_Audience_Scores[[#This Row],[Year]],10) -> 1990
A9: 8 | B9: City Lights | C9: 1931 | D9: Comedy, Drama, Romance | E9: Charlie Chaplin | F9: en | G9: 3 wins. | H9: Twentieth Century Fox Home Entertainment | I9: 91 | J9: 8.5 | K9: 85 | L9: 205619 | M9: 99 | N9: 94 | O9: 52 | P9: 92 | Q9: 66173 | R9: 86 | S9: 144013 | T9: 92 | U9: itunes, amzvid, hbm | V9: 91.33 | W9: =Top_500_Movies_Ranked_by_Combined_Critics_and_Audience_Scores[[#This Row],[Critic_Rating_RT]]-Top_500_Movies_Ranked_by_Combined_Critics_and_Audience_Scores[[#This Row],[Audience_Rating]] -> 2 | X9: =FLOOR(Top_500_Movies_Ranked_by_Combined_Critics_and_Audience_Scores[[#This Row],[Year]],10) -> 1930
A10: 9 | B10: Spirited Away | C10: 2001 | D10: Animation, Family, Fantasy | E10: Hayao Miyazaki | F10: ja | G10: Won 1 Oscar. Another 51 wins & 22 nominations. | H10: Walt Disney Pictures | I10: 90 | J10: 8.6 | K10: 86 | L10: 901217 | M10: 96 | N10: 89 | O10: 134 | P10: 93 | Q10: 1052053 | R10: 88 | S10: 2478980 | T10: 95 | U10: itunes, amzvid, hbm | V10: 91.17 | W10: =Top_500_Movies_Ranked_by_Combined_Critics_and_Audience_Scores[[#This Row],[Critic_Rating_RT]]-Top_500_Movies_Ranked_by_Combined_Critics_and_Audience_Scores[[#This Row],[Audience_Rating]] -> -4 | X10: =FLOOR(Top_500_Movies_Ranked_by_Combined_Critics_and_Audience_Scores[[#This Row],[Year]],10) -> 2000
A11: 10 | B11: Parasite | C11: 2019 | D11: Comedy, Thriller, Drama | E11: Bong Joon Ho | F11: ko | I11: 91 | J11: 8.5 | K11: 85 | L11: 1050592 | M11: 97 | N11: 95 | O11: 314 | P11: 88 | Q11: 1273882 | R11: 90 | S11: 3771374 | T11: 90 | U11: itunes, amzvid | V11: 90.83 | W11: =Top_500_Movies_Ranked_by_Combined_Critics_and_Audience_Scores[[#This Row],[Critic_Rating_RT]]-Top_500_Movies_Ranked_by_Combined_Critics_and_Audience_Scores[[#This Row],[Audience_Rating]] -> 7 | X11: =FLOOR(Top_500_Movies_Ranked_by_Combined_Critics_and_Audience_Scores[[#This Row],[Year]],10) -> 2010
A12: 11 | B12: Modern Times | C12: 1936 | D12: Comedy, Drama, Romance | E12: Charlie Chaplin | F12: en | G12: 3 wins & 1 nomination. | H12: United Artists | I12: 90 | J12: 8.5 | K12: 85 | L12: 271086 | M12: 96 | N12: 95 | O12: 72 | P12: 92 | Q12: 97048 | R12: 86 | S12: 210247 | T12: 90 | U12: prime, itunes, amzvid, hbm | V12: 90.67 | W12: =Top_500_Movies_Ranked_by_Combined_Critics_and_Audience_Scores[[#This Row],[Critic_Rating_RT]]-Top_500_Movies_Ranked_by_Combined_Critics_and_Audience_Scores[[#This Row],[Audience_Rating]] -> 3 | X12: =FLOOR(Top_500_Movies_Ranked_by_Combined_Critics_and_Audience_Scores[[#This Row],[Year]],10) -> 1930
A13: 12 | B13: Goodfellas | C13: 1990 | D13: Drama, Crime | E13: Martin Scorsese | F13: en | G13: Won 1 Oscar. Another 42 wins & 24 nominations. | H13: Warner Bros. | I13: 90 | J13: 8.7 | K13: 87 | L13: 1315490 | M13: 92 | N13: 91 | O13: 95 | P13: 94 | Q13: 766130 | R13: 90 | S13: 1435501 | T13: 89 | U13: prime, itunes, amzvid, hbm | V13: 90.5 | W13: =Top_500_Movies_Ranked_by_Combined_Critics_and_Audience_Scores[[#This Row],[Critic_Rating_RT]]-Top_500_Movies_Ranked_by_Combined_Critics_and_Audience_Scores[[#This Row],[Audience_Rating]] -> -3 | X13: =FLOOR(Top_500_Movies_Ranked_by_Combined_Critics_and_Audience_Scores[[#This Row],[Year]],10) -> 1990
A14: 13 | B14: The Good, the Bad and the Ugly | C14: 1966 | D14: Western | E14: Sergio Leone | F14: it | G14: 1 win. | H14: United Artists | I14: 89 | J14: 8.8 | K14: 88 | L14: 847249 | M14: 90 | N14: 89 | O14: 58 | P14: 94 | Q14: 328668 | R14: 90 | S14: 504912 | T14: 91 | U14: itunes, amzvid | V14: 90.33 | W14: =Top_500_Movies_Ranked_by_Combined_Critics_and_Audience_Scores[[#This Row],[Critic_Rating_RT]]-Top_500_Movies_Ranked_by_Combined_Critics_and_Audience_Scores[[#This Row],[Audience_Rating]] -> -5 | X14: =FLOOR(Top_500_Movies_Ranked_by_Combined_Critics_and_Audience_Scores[[#This Row],[Year]],10) -> 1960
A15: 14 | B15: Dr. Strangelove or: How I Learned to Stop Worrying and Love the Bomb | C15: 1964 | D15: Comedy, War | E15: Stanley Kubrick | F15: en | G15: Nominated for 4 Oscars. Another 15 wins & 4 nominations. | H15: Sony Pictures | I15: 90 | J15: 8.3 | K15: 83 | L15: 535648 | M15: 97 | N15: 93 | O15: 87 | P15: 90 | Q15: 298335 | R15: 86 | S15: 475057 | T15: 92 | U15: itunes, amzvid | V15: 90.17 | W15: =Top_500_Movies_Ranked_by_Combined_Critics_and_Audience_Scores[[#This Row],[Critic_Rating_RT]]-Top_500_Movies_Ranked_by_Combined_Critics_and_Audience_Scores[[#This Row],[Audience_Rating]] -> 3 | X15: =FLOOR(Top_500_Movies_Ranked_by_Combined_Critics_and_Audience_Scores[[#This Row],[Year]],10) -> 1960
A16: 15 | B16: Casablanca | C16: 1942 | D16: Drama, Romance | E16: Michael Curtiz | F16: en | G16: Won 3 Oscars. Another 6 wins & 6 nominations. | H16: Warner Bros. Pictures | I16: 90 | J16: 8.5 | K16: 85 | L16: 628003 | M16: 100 | N16: 96 | O16: 96 | P16: 91 | Q16: 429846 | R16: 86 | S16: 572792 | T16: 83 | U16: hbo, itunes, amzvid, hbm | V16: 90.17 | W16: =Top_500_Movies_Ranked_by_Combined_Critics_and_Audience_Scores[[#This Row],[Critic_Rating_RT]]-Top_500_Movies_Ranked_by_Combined_Critics_and_Audience_Scores[[#This Row],[Audience_Rating]] -> 5 | X16: =FLOOR(Top_500_Movies_Ranked_by_Combined_Critics_and_Audience_Scores[[#This Row],[Year]],10) -> 1940
A17: 16 | B17: The Battle of Algiers | C17: 1966 | D17: Drama, War, History | E17: Gillo Pontecorvo | F17: it | G17: Nominated for 3 Oscars. Another 11 wins & 3 nominations. | H17: Rialto Pictures | I17: 90 | J17: 8.1 | K17: 81 | L17: 70309 | M17: 96 | N17: 92 | O17: 67 | P17: 91 | Q17: 37316 | R17: 88 | S17: 82844 | T17: 92 | U17: itunes, amzvid, hbm | V17: 90 | W17: =Top_500_Movies_Ranked_by_Combined_Critics_and_Audience_Scores[[#This Row],[Critic_Rating_RT]]-Top_500_Movies_Ranked_by_Combined_Critics_and_Audience_Scores[[#This Row],[Audience_Rating]] -> 1 | X17: =FLOOR(Top_500_Movies_Ranked_by_Combined_Critics_and_Audience_Scores[[#This Row],[Year]],10) -> 1960
A18: 17 | B18: Singin' in the Rain | C18: 1952 | D18: Comedy, Romance | E18: Stanley Donen, Gene Kelly | F18: en | G18: Nominated for 2 Oscars. Another 5 wins & 7 nominations. | H18: MGM | I18: 90 | J18: 8.3 | K18: 83 | L18: 270897 | M18: 99 | N18: 95 | O18: 62 | P18: 91 | Q18: 242729 | R18: 86 | S18: 450117 | T18: 86 | U18: hbo, itunes, amzvid, hbm | V18: 90 | W18: =Top_500_Movies_Ranked_by_Combined_Critics_and_Audience_Scores[[#This Row],[Critic_Rating_RT]]-Top_500_Movies_Ranked_by_Combined_Critics_and_Audience_Scores[[#This Row],[Audience_Rating]] -> 4 | X18: =FLOOR(Top_500_Movies_Ranked_by_Combined_Critics_and_Audience_Scores[[#This Row],[Year]],10) -> 1950
A19: 18 | B19: Some Like It Hot | C19: 1959 | D19: Comedy, Romance, Crime | E19: Billy Wilder | F19: en | G19: Won 1 Oscar. Another 9 wins & 13 nominations. | H19: United Artists | I19: 89 | J19: 8.2 | K19: 82 | L19: 293363 | M19: 98 | N19: 93 | O19: 77 | P19: 90 | Q19: 143114 | R19: 86 | S19: 264180 | T19: 90 | U19: prime, itunes, amzvid | V19: 89.83 | W19: =Top_500_Movies_Ranked_by_Combined_Critics_and_Audience_Scores[[#This Row],[Critic_Rating_RT]]-Top_500_Movies_Ranked_by_Combined_Critics_and_Audience_Scores[[#This Row],[Audience_Rating]] -> 3 | X19: =FLOOR(Top_500_Movies_Ranked_by_Combined_Critics_and_Audience_Scores[[#This Row],[Year]],10) -> 1950
A20: 19 | B20: Psycho | C20: 1960 | D20: Horror, Thriller, Mystery | E20: Alfred Hitchcock | F20: en | G20: Nominated for 4 Oscars. Another 7 wins & 5 nominations. | H20: Paramount Pictures | I20: 89 | J20: 8.5 | K20: 85 | L20: 748078 | M20: 97 | N20: 94 | O20: 97 | P20: 92 | Q20: 491167 | R20: 86 | S20: 991319 | T20: 85 | U20: itunes, amzvid | V20: 89.83 | W20: =Top_500_Movies_Ranked_by_Combined_Critics_and_Audience_Scores[[#This Row],[Critic_Rating_RT]]-Top_500_Movies_Ranked_by_Combined_Critics_and_Audience_Scores[[#This Row],[Audience_Rating]] -> 2 | X20: =FLOOR(Top_500_Movies_Ranked_by_Combined_Critics_and_Audience_Scores[[#This Row],[Year]],10) -> 1960
A21: 20 | B21: Apocalypse Now | C21: 1979 | D21: Drama, War | E21: Francis Ford Coppola | F21: en | G21: Won 2 Oscars. Another 20 wins & 30 nominations. | H21: United Artists | I21: 89 | J21: 8.4 | K21: 84 | L21: 737539 | M21: 94 | N21: 92 | O21: 117 | P21: 91 | Q21: 429279 | R21: 88 | S21: 714063 | T21: 89 | U21: itunes, amzvid | V21: 89.67 | W21: =Top_500_Movies_Ranked_by_Combined_Critics_and_Audience_Scores[[#This Row],[Critic_Rating_RT]]-Top_500_Movies_Ranked_by_Combined_Critics_and_Audience_Scores[[#This Row],[Audience_Rating]] -> 1 | X21: =FLOOR(Top_500_Movies_Ranked_by_Combined_Critics_and_Audience_Scores[[#This Row],[Year]],10) -> 1970
A22: 21 | B22: Double Indemnity | C22: 1944 | D22: Crime, Thriller | E22: Billy Wilder | F22: en | G22: Nominated for 7 Oscars. Another 2 wins & 2 nominations. | H22: Paramount Pictures | I22: 89 | J22: 8.3 | K22: 83 | L22: 173790 | M22: 95 | N22: 93 | O22: 72 | P22: 91 | Q22: 79935 | R22: 86 | S22: 167927 | T22: 89 | U22: prime, itunes, amzvid | V22: 89.5 | W22: =Top_500_Movies_Ranked_by_Combined_Critics_and_Audience_Scores[[#This Row],[Critic_Rating_RT]]-Top_500_Movies_Ranked_by_Combined_Critics_and_Audience_Scores[[#This Row],[Audience_Rating]] -> 2 | X22: =FLOOR(Top_500_Movies_Ranked_by_Combined_Critics_and_Audience_Scores[[#This Row],[Year]],10) -> 1940
A23: 22 | B23: Rashomon | C23: 1950 | D23: Crime, Drama, Mystery | E23: Akira Kurosawa | F23: ja | I23: 89 | J23: 8.2 | K23: 82 | L23: 188349 | M23: 98 | N23: 94 | O23: 52 | P23: 90 | Q23: 105423 | R23: 84 | S23: 219549 | T23: 88 | U23: itunes, amzvid, hbm | V23: 89.33 | W23: =Top_500_Movies_Ranked_by_Combined_Critics_and_Audience_Scores[[#This Row],[Critic_Rating_RT]]-Top_500_Movies_Ranked_by_Combined_Critics_and_Audience_Scores[[#This Row],[Audience_Rating]] -> 4 | X23: =FLOOR(Top_500_Movies_Ranked_by_Combined_Critics_and_Audience_Scores[[#This Row],[Year]],10) -> 1950
A24: 23 | B24: Lawrence of Arabia | C24: 1962 | D24: Adventure, History, War | E24: David Lean | F24: en | G24: Won 7 Oscars. Another 22 wins & 15 nominations. | H24: Columbia Pictures | I24: 89 | J24: 8.3 | K24: 83 | L24: 327276 | M24: 100 | N24: 96 | O24: 82 | P24: 89 | Q24: 129761 | R24: 88 | S24: 238330 | T24: 80 | U24: itunes, amzvid | V24: 89.33 | W24: =Top_500_Movies_Ranked_by_Combined_Critics_and_Audience_Scores[[#This Row],[Critic_Rating_RT]]-Top_500_Movies_Ranked_by_Combined_Critics_and_Audience_Scores[[#This Row],[Audience_Rating]] -> 7 | X24: =FLOOR(Top_500_Movies_Ranked_by_Combined_Critics_and_Audience_Scores[[#This Row],[Year]],10) -> 1960
A25: 24 | B25: All About Eve | C25: 1950 | D25: Drama | E25: Joseph L. Mankiewicz | F25: en | G25: Won 6 Oscars. Another 16 wins & 17 nominations. | H25: 20th Century Fox | I25: 89 | J25: 8.2 | K25: 82 | L25: 143727 | M25: 98 | N25: 95 | O25: 73 | P25: 90 | Q25: 66740 | R25: 88 | S25: 109394 | T25: 83 | U25: itunes, amzvid | V25: 89.33 | W25: =Top_500_Movies_Ranked_by_Combined_Critics_and_Audience_Scores[[#This Row],[Critic_Rating_RT]]-Top_500_Movies_Ranked_by_Combined_Critics_and_Audience_Scores[[#This Row],[Audience_Rating]] -> 5 | X25: =FLOOR(Top_500_Movies_Ranked_by_Combined_Critics_and_Audience_Scores[[#This Row],[Year]],10) -> 1950
A26: 25 | B26: Portrait of a Lady on Fire | C26: 2019 | D26: Drama, Romance, History | E26: Céline Sciamma | F26: fr | I26: 89 | J26: 8.1 | K26: 81 | L26: 117917 | M26: 95 | N26: 91 | O26: 197 | P26: 89 | Q26: 275015 | R26: 88 | S26: 819613 | T26: 91 | U26: itunes | V26: 89.17 | W26: =Top_500_Movies_Ranked_by_Combined_Critics_and_Audience_Scores[[#This Row],[Critic_Rating_RT]]-Top_500_Movies_Ranked_by_Combined_Critics_and_Audience_Scores[[#This Row],[Audience_Rating]] -> 2 | X26: =FLOOR(Top_500_Movies_Ranked_by_Combined_Critics_and_Audience_Scores[[#This Row],[Year]],10) -> 2010
A27: 26 | B27: A Separation | C27: 2011 | D27: Drama | E27: Asghar Farhadi | F27: fa | G27: Won 1 Oscar. Another 84 wins & 30 nominations. | H27: Sony Pictures Classics | I27: 89 | J27: 8.3 | K27: 83 | L27: 267944 | M27: 95 | N27: 91 | O27: 117 | P27: 88 | Q27: 62517 | R27: 88 | S27: 141543 | T27: 89 | U27: itunes, amzvid | V27: 89 | W27: =Top_500_Movies_Ranked_by_Combined_Critics_and_Audience_Scores[[#This Row],[Critic_Rating_RT]]-Top_500_Movies_Ranked_by_Combined_Critics_and_Audience_Scores[[#This Row],[Audience_Rating]] -> 3 | X27: =FLOOR(Top_500_Movies_Ranked_by_Combined_Critics_and_Audience_Scores[[#This Row],[Year]],10) -> 2010
A28: 27 | B28: One Battle After Another | C28: 2025 | D28: Action, Thriller, Crime | E28: Paul Thomas Anderson | F28: en | I28: 89 | J28: 8.2 | K28: 82 | L28: 115333 | M28: 95 | N28: 91 | O28: 211 | R28: 88 | V28: 89 | W28: =Top_500_Movies_Ranked_by_Combined_Critics_and_Audience_Scores[[#This Row],[Critic_Rating_RT]]-Top_500_Movies_Ranked_by_Combined_Critics_and_Audience_Scores[[#This Row],[Audience_Rating]] -> 91 | X28: =FLOOR(Top_500_Movies_Ranked_by_Combined_Critics_and_Audience_Scores[[#This Row],[Year]],10) -> 2020
A29: 28 | B29: The Lord of the Rings: The Return of the King | C29: 2003 | D29: Adventure, Fantasy, Action | E29: Peter Jackson | F29: en | G29: Won 11 Oscars. Another 164 wins & 87 nominations. | H29: New Line Cinema | I29: 89 | J29: 9 | K29: 90 | L29: 2064721 | M29: 94 | N29: 89 | O29: 172 | P29: 85 | Q29: 23617405 | R29: 90 | S29: 1492669 | T29: 85 | U29: hbo, itunes, amzvid, hbm | V29: 88.83 | W29: =Top_500_Movies_Ranked_by_Combined_Critics_and_Audience_Scores[[#This Row],[Critic_Rating_RT]]-Top_500_Movies_Ranked_by_Combined_Critics_and_Audience_Scores[[#This Row],[Audience_Rating]] -> 4 | X29: =FLOOR(Top_500_Movies_Ranked_by_Combined_Critics_and_Audience_Scores[[#This Row],[Year]],10) -> 2000
A30: 29 | B30: Citizen Kane | C30: 1941 | D30: Mystery, Drama | E30: Orson Welles | F30: en | G30: Won 1 Oscar. Another 8 wins & 10 nominations. | H30: RKO Radio Pictures | I30: 89 | J30: 8.3 | K30: 83 | L30: 478970 | M30: 100 | N30: 98 | O30: 96 | P30: 87 | Q30: 273099 | R30: 84 | S30: 499118 | T30: 81 | U30: itunes, amzvid, hbm | V30: 88.83 | W30: =Top_500_Movies_Ranked_by_Combined_Critics_and_Audience_Scores[[#This Row],[Critic_Rating_RT]]-Top_500_Movies_Ranked_by_Combined_Critics_and_Audience_Scores[[#This Row],[Audience_Rating]] -> 11 | X30: =FLOOR(Top_500_Movies_Ranked_by_Combined_Critics_and_Audience_Scores[[#This Row],[Year]],10) -> 1940
A31: 30 | B31: Metropolis | C31: 1927 | D31: Drama, Science Fiction | E31: Fritz Lang | F31: de | G31: 3 wins & 4 nominations. | H31: Paramount Pictures | I31: 88 | J31: 8.3 | K31: 83 | L31: 193052 | M31: 98 | N31: 93 | O31: 99 | P31: 89 | Q31: 108894 | R31: 86 | S31: 200533 | T31: 84 | U31: itunes, amzvid | V31: 88.83 | W31: =Top_500_Movies_Ranked_by_Combined_Critics_and_Audience_Scores[[#This Row],[Critic_Rating_RT]]-Top_500_Movies_Ranked_by_Combined_Critics_and_Audience_Scores[[#This Row],[Audience_Rating]] -> 4 | X31: =FLOOR(Top_500_Movies_Ranked_by_Combined_Critics_and_Audience_Scores[[#This Row],[Year]],10) -> 1920
A32: 31 | B32: It's a Wonderful Life | C32: 1946 | D32: Drama, Family, Fantasy | E32: Frank Capra | F32: en | G32: Nominated for 5 Oscars. Another 7 wins. | H32: Liberty Films | I32: 88 | J32: 8.6 | K32: 86 | L32: 524890 | M32: 89 | N32: 90 | O32: 75 | P32: 92 | Q32: 320749 | R32: 88 | S32: 522501 | T32: 88 | U32: prime, itunes, amzvid | V32: 88.83 | W32: =Top_500_Movies_Ranked_by_Combined_Critics_and_Audience_Scores[[#This Row],[Critic_Rating_RT]]-Top_500_Movies_Ranked_by_Combined_Critics_and_Audience_Scores[[#This Row],[Audience_Rating]] -> -2 | X32: =FLOOR(Top_500_Movies_Ranked_by_Combined_Critics_and_Audience_Scores[[#This Row],[Year]],10) -> 1940
A33: 32 | B33: Sunset Blvd. | C33: 1950 | D33: Drama | E33: Billy Wilder | F33: en | G33: Won 3 Oscars. Another 19 wins & 14 nominations. | H33: Paramount Pictures | I33: 88 | J33: 8.4 | K33: 84 | L33: 247384 | M33: 94 | N33: 95 | O33: 89 | P33: 92 | Q33: 123301 | R33: 88 | S33: 262498 | T33: 80 | U33: itunes, amzvid | V33: 88.83 | W33: =Top_500_Movies_Ranked_by_Combined_Critics_and_Audience_Scores[[#This Row],[Critic_Rating_RT]]-Top_500_Movies_Ranked_by_Combined_Critics_and_Audience_Scores[[#This Row],[Audience_Rating]] -> 3 | X33: =FLOOR(Top_500_Movies_Ranked_by_Combined_Critics_and_Audience_Scores[[#This Row],[Year]],10) -> 1950
A34: 33 | B34: The Lord of the Rings: The Fellowship of the Ring | C34: 2001 | D34: Adventure, Fantasy, Action | E34: Peter Jackson | F34: en | G34: Won 4 Oscars. Another 110 wins & 100 nominations. | H34: New Line Cinema | I34: 87 | J34: 8.9 | K34: 89 | L34: 2094033 | M34: 92 | N34: 85 | O34: 142 | P34: 92 | Q34: 1546965 | R34: 88 | S34: 1929394 | T34: 86 | U34: hbo, itunes, amzvid, hbm | V34: 88.67 | W34: =Top_500_Movies_Ranked_by_Combined_Critics_and_Audience_Scores[[#This Row],[Critic_Rating_RT]]-Top_500_Movies_Ranked_by_Combined_Critics_and_Audience_Scores[[#This Row],[Audience_Rating]] -> -7 | X34: =FLOOR(Top_500_Movies_Ranked_by_Combined_Critics_and_Audience_Scores[[#This Row],[Year]],10) -> 2000
A35: 34 | B35: North by Northwest | C35: 1959 | D35: Thriller, Adventure | E35: Alfred Hitchcock | F35: en | G35: Nominated for 3 Oscars. Another 8 wins & 4 nominations. | H35: Turner Entertainment | I35: 88 | J35: 8.3 | K35: 83 | L35: 358883 | M35: 98 | N35: 94 | O35: 90 | P35: 90 | Q35: 142001 | R35: 84 | S35: 265857 | T35: 83 | U35: itunes, amzvid, hbm | V35: 88.67 | W35: =Top_500_Movies_Ranked_by_Combined_Critics_and_Audience_Scores[[#This Row],[Critic_Rating_RT]]-Top_500_Movies_Ranked_by_Combined_Critics_and_Audience_Scores[[#This Row],[Audience_Rating]] -> 4 | X35: =FLOOR(Top_500_Movies_Ranked_by_Combined_Critics_and_Audience_Scores[[#This Row],[Year]],10) -> 1950
A36: 35 | B36: The Apartment | C36: 1960 | D36: Comedy, Drama, Romance | E36: Billy Wilder | F36: en | G36: Won 5 Oscars. Another 19 wins & 8 nominations. | H36: United Artists | I36: 88 | J36: 8.3 | K36: 83 | L36: 207527 | M36: 94 | N36: 90 | O36: 93 | P36: 91 | Q36: 109780 | R36: 88 | S36: 252510 | T36: 86 | U36: itunes, amzvid | V36: 88.67 | W36: =Top_500_Movies_Ranked_by_Combined_Critics_and_Audience_Scores[[#This Row],[Critic_Rating_RT]]-Top_500_Movies_Ranked_by_Combined_Critics_and_Audience_Scores[[#This Row],[Audience_Rating]] -> -1 | X36: =FLOOR(Top_500_Movies_Ranked_by_Combined_Critics_and_Audience_Scores[[#This Row],[Year]],10) -> 1960
A37: 36 | B37: One Flew Over the Cuckoo's Nest | C37: 1975 | D37: Drama | E37: Miloš Forman | F37: en | G37: Won 5 Oscars. Another 31 wins & 12 nominations. | H37: United Artists | I37: 88 | J37: 8.7 | K37: 87 | L37: 1110492 | M37: 84 | N37: 89 | O37: 91 | P37: 93 | Q37: 421045 | R37: 88 | S37: 702258 | T37: 91 | U37: itunes | V37: 88.67 | W37: =Top_500_Movies_Ranked_by_Combined_Critics_and_Audience_Scores[[#This Row],[Critic_Rating_RT]]-Top_500_Movies_Ranked_by_Combined_Critics_and_Audience_Scores[[#This Row],[Audience_Rating]] -> -4 | X37: =FLOOR(Top_500_Movies_Ranked_by_Combined_Critics_and_Audience_Scores[[#This Row],[Year]],10) -> 1970
A38: 37 | B38: Star Wars: Episode V - The Empire Strikes Back | C38: 1980 | D38: Adventure, Action, Science Fiction | E38: Irvin Kershner | F38: en | G38: Won 1 Oscar. Another 15 wins & 17 nominations. | H38: Twentieth Century Fox | I38: 88 | J38: 8.7 | K38: 87 | L38: 1431491 | M38: 82 | N38: 88 | O38: 81 | P38: 93 | Q38: 1214408 | R38: 88 | S38: 1521674 | T38: 94 | U38: disney, itunes, amzvid | V38: 88.67 | W38: =Top_500_Movies_Ranked_by_Combined_Critics_and_Audience_Scores[[#This Row],[Critic_Rating_RT]]-Top_500_Movies_Ranked_by_Combined_Critics_and_Audience_Scores[[#This Row],[Audience_Rating]] -> -5 | X38: =FLOOR(Top_500_Movies_Ranked_by_Combined_Critics_and_Audience_Scores[[#This Row],[Year]],10) -> 1980
A39: 38 | B39: Whiplash | C39: 2014 | D39: Drama, Music | E39: Damien Chazelle | F39: en | G39: Won 3 Oscars. Another 87 wins & 99 nominations. | H39: Sony Pictures Classics | I39: 88 | J39: 8.5 | K39: 85 | L39: 1063607 | M39: 89 | N39: 87 | O39: 231 | P39: 91 | Q39: 1025887 | R39: 88 | S39: 2932518 | T39: 92 | U39: itunes, amzvid | V39: 88.67 | W39: =Top_500_Movies_Ranked_by_Combined_Critics_and_Audience_Scores[[#This Row],[Critic_Rating_RT]]-Top_500_Movies_Ranked_by_Combined_Critics_and_Audience_Scores[[#This Row],[Audience_Rating]] -> -4 | X39: =FLOOR(Top_500_Movies_Ranked_by_Combined_Critics_and_Audience_Scores[[#This Row],[Year]],10) -> 2010
A40: 39 | B40: Vertigo | C40: 1958 | D40: Mystery, Romance, Thriller | E40: Alfred Hitchcock | F40: en | G40: Nominated for 2 Oscars. Another 8 wins & 3 nominations. | H40: Paramount Pictures | I40: 88 | J40: 8.3 | K40: 83 | L40: 442662 | M40: 100 | N40: 92 | O40: 78 | P40: 90 | Q40: 267419 | R40: 84 | S40: 596103 | T40: 83 | U40: itunes, amzvid | V40: 88.67 | W40: =Top_500_Movies_Ranked_by_Combined_Critics_and_Audience_Scores[[#This Row],[Critic_Rating_RT]]-Top_500_Movies_Ranked_by_Combined_Critics_and_Audience_Scores[[#This Row],[Audience_Rating]] -> 2 | X40: =FLOOR(Top_500_Movies_Ranked_by_Combined_Critics_and_Audience_Scores[[#This Row],[Year]],10) -> 1950
A41: 40 | B41: Bicycle Thieves | C41: 1948 | D41: Drama | E41: Vittorio De Sica | F41: it | G41: Nominated for 1 Oscar. Another 18 wins. | H41: ENIC | I41: 87 | J41: 8.2 | K41: 82 | L41: 184016 | N41: 93 | O41: 58 | P41: 91 | Q41: 93336 | R41: 86 | S41: 211270 | T41: 91 | U41: itunes, amzvid, hbm | V41: 88.6 | W41: =Top_500_Movies_Ranked_by_Combined_Critics_and_Audience_Scores[[#This Row],[Critic_Rating_RT]]-Top_500_Movies_Ranked_by_Combined_Critics_and_Audience_Scores[[#This Row],[Audience_Rating]] -> 2 | X41: =FLOOR(Top_500_Movies_Ranked_by_Combined_Critics_and_Audience_Scores[[#This Row],[Year]],10) -> 1940
A42: 41 | B42: Ran | C42: 1985 | D42: Action, Drama, History | E42: Akira Kurosawa | F42: ja | G42: Won 1 Oscar. Another 29 wins & 18 nominations. | H42: Rialto Pictures | I42: 88 | J42: 8.2 | K42: 82 | L42: 142429 | M42: 97 | N42: 92 | O42: 73 | P42: 91 | Q42: 80147 | R42: 90 | S42: 163420 | T42: 79 | U42: itunes, amzvid | V42: 88.5 | W42: =Top_500_Movies_Ranked_by_Combined_Critics_and_Audience_Scores[[#This Row],[Critic_Rating_RT]]-Top_500_Movies_Ranked_by_Combined_Critics_and_Audience_Scores[[#This Row],[Audience_Rating]] -> 1 | X42: =FLOOR(Top_500_Movies_Ranked_by_Combined_Critics_and_Audience_Scores[[#This Row],[Year]],10) -> 1980
A43: 42 | B43: Pan's Labyrinth | C43: 2006 | D43: Fantasy, Drama, War | E43: Guillermo del Toro | F43: es | G43: Won 3 Oscars. Another 103 wins & 72 nominations. | H43: Picturehouse | I43: 88 | J43: 8.2 | K43: 82 | L43: 721982 | M43: 98 | N43: 89 | O43: 164 | P43: 87 | Q43: 672087 | R43: 84 | S43: 741536 | T43: 91 | U43: itunes, amzvid | V43: 88.5 | W43: =Top_500_Movies_Ranked_by_Combined_Critics_and_Audience_Scores[[#This Row],[Critic_Rating_RT]]-Top_500_Movies_Ranked_by_Combined_Critics_and_Audience_Scores[[#This Row],[Audience_Rating]] -> 2 | X43: =FLOOR(Top_500_Movies_Ranked_by_Combined_Critics_and_Audience_Scores[[#This Row],[Year]],10) -> 2000
A44: 43 | B44: The Third Man | C44: 1949 | D44: Thriller, Mystery | E44: Carol Reed | F44: en | G44: Won 1 Oscar. Another 4 wins & 4 nominations. | H44: Rialto Pictures | I44: 88 | J44: 8.1 | K44: 81 | L44: 188727 | M44: 97 | N44: 95 | O44: 81 | P44: 89 | Q44: 86513 | R44: 86 | S44: 151068 | T44: 83 | U44: prime, itunes, amzvid | V44: 88.5 | W44: =Top_500_Movies_Ranked_by_Combined_Critics_and_Audience_Scores[[#This Row],[Critic_Rating_RT]]-Top_500_Movies_Ranked_by_Combined_Critics_and_Audience_Scores[[#This Row],[Audience_Rating]] -> 6 | X44: =FLOOR(Top_500_Movies_Ranked_by_Combined_Critics_and_Audience_Scores[[#This Row],[Year]],10) -> 1940
A45: 44 | B45: Star Wars: Episode IV - A New Hope | C45: 1977 | D45: Adventure, Action, Science Fiction | E45: George Lucas | F45: en | G45: Won 6 Oscars. Another 38 wins & 27 nominations. | H45: 20th Century Fox | I45: 88 | J45: 8.6 | K45: 86 | L45: 1498734 | M45: 90 | N45: 89 | O45: 99 | P45: 92 | Q45: 1163061 | R45: 84 | S45: 1758149 | T45: 90 | U45: disney, itunes, amzvid | V45: 88.5 | W45: =Top_500_Movies_Ranked_by_Combined_Critics_and_Audience_Scores[[#This Row],[Critic_Rating_RT]]-Top_500_Movies_Ranked_by_Combined_Critics_and_Audience_Scores[[#This Row],[Audience_Rating]] -> -3 | X45: =FLOOR(Top_500_Movies_Ranked_by_Combined_Critics_and_Audience_Scores[[#This Row],[Year]],10) -> 1970
A46: 45 | B46: 12 Years a Slave | C46: 2013 | D46: Drama, History | E46: Steve McQueen | F46: en | I46: 88 | J46: 8.1 | K46: 81 | L46: 761724 | M46: 96 | N46: 91 | O46: 244 | P46: 87 | Q46: 278959 | R46: 84 | S46: 554833 | T46: 91 | U46: itunes, amzvid, hbm | V46: 88.33 | W46: =Top_500_Movies_Ranked_by_Combined_Critics_and_Audience_Scores[[#This Row],[Critic_Rating_RT]]-Top_500_Movies_Ranked_by_Combined_Critics_and_Audience_Scores[[#This Row],[Audience_Rating]] -> 4 | X46: =FLOOR(Top_500_Movies_Ranked_by_Combined_Critics_and_Audience_Scores[[#This Row],[Year]],10) -> 2010
A47: 46 | B47: Saving Private Ryan | C47: 1998 | D47: Drama, History, War | E47: Steven Spielberg | F47: en | G47: Won 5 Oscars. Another 78 wins & 66 nominations. | H47: Paramount Pictures | I47: 88 | J47: 8.6 | K47: 86 | L47: 1559687 | M47: 91 | N47: 87 | O47: 91 | P47: 91 | Q47: 1004841 | R47: 84 | S47: 1024759 | T47: 91 | U47: netflix, prime, paramount, itunes, amzvid | V47: 88.33 | W47: =Top_500_Movies_Ranked_by_Combined_Critics_and_Audience_Scores[[#This Row],[Critic_Rating_RT]]-Top_500_Movies_Ranked_by_Combined_Critics_and_Audience_Scores[[#This Row],[Audience_Rating]] -> -4 | X47: =FLOOR(Top_500_Movies_Ranked_by_Combined_Critics_and_Audience_Scores[[#This Row],[Year]],10) -> 1990
A48: 47 | B48: WALL·E | C48: 2008 | D48: Animation, Family, Science Fiction | E48: Andrew Stanton | F48: en | G48: Won 1 Oscar. Another 84 wins & 65 nominations. | H48: Walt Disney Pictures | I48: 88 | J48: 8.4 | K48: 84 | L48: 1252363 | M48: 95 | N48: 88 | O48: 152 | P48: 87 | Q48: 1014430 | R48: 84 | S48: 1843873 | T48: 92 | U48: disney, itunes, amzvid | V48: 88.33 | W48: =Top_500_Movies_Ranked_by_Combined_Critics_and_Audience_Scores[[#This Row],[Critic_Rating_RT]]-Top_500_Movies_Ranked_by_Combined_Critics_and_Audience_Scores[[#This Row],[Audience_Rating]] -> 1 | X48: =FLOOR(Top_500_Movies_Ranked_by_Combined_Critics_and_Audience_Scores[[#This Row],[Year]],10) -> 2000
A49: 48 | B49: Alien | C49: 1979 | D49: Horror, Science Fiction | E49: Ridley Scott | F49: en | G49: Won 1 Oscar. Another 15 wins & 19 nominations. | H49: 20th Century Fox | I49: 88 | J49: 8.5 | K49: 85 | L49: 1009344 | M49: 89 | N49: 91 | O49: 139 | P49: 91 | Q49: 764014 | R49: 86 | S49: 1368049 | T49: 88 | U49: hbo, itunes, amzvid | V49: 88.33 | W49: =Top_500_Movies_Ranked_by_Combined_Critics_and_Audience_Scores[[#This Row],[Critic_Rating_RT]]-Top_500_Movies_Ranked_by_Combined_Critics_and_Audience_Scores[[#This Row],[Audience_Rating]] -> 0 | X49: =FLOOR(Top_500_Movies_Ranked_by_Combined_Critics_and_Audience_Scores[[#This Row],[Year]],10) -> 1970
A50: 49 | B50: The 400 Blows | C50: 1959 | D50: Drama | E50: François Truffaut | F50: fr | G50: Nominated for 1 Oscar. Another 7 wins & 3 nominations. | H50: Zenith International Films | I50: 87 | J50: 8 | K50: 80 | L50: 131044 | N50: 95 | O50: 66 | P50: 90 | Q50: 98670 | R50: 86 | S50: 218210 | T50: 90 | U50: itunes, amzvid, hbm | V50: 88.2 | W50: =Top_500_Movies_Ranked_by_Combined_Critics_and_Audience_Scores[[#This Row],[Critic_Rating_RT]]-Top_500_Movies_Ranked_by_Combined_Critics_and_Audience_Scores[[#This Row],[Audience_Rating]] -> 5 | X50: =FLOOR(Top_500_Movies_Ranked_by_Combined_Critics_and_Audience_Scores[[#This Row],[Year]],10) -> 1950
A51: 50 | B51: The Silence of the Lambs | C51: 1991 | D51: Crime, Drama, Thriller | E51: Jonathan Demme | F51: en | G51: Won 5 Oscars. Another 51 wins & 30 nominations. | H51: Orion Pictures Corporation | I51: 87 | J51: 8.6 | K51: 86 | L51: 1622286 | M51: 86 | N51: 88 | O51: 112 | P51: 92 | Q51: 1226259 | R51: 86 | S51: 1981219 | T51: 91 | U51: itunes, amzvid | V51: 88.17 | W51: =Top_500_Movies_Ranked_by_Combined_Critics_and_Audience_Scores[[#This Row],[Critic_Rating_RT]]-Top_500_Movies_Ranked_by_Combined_Critics_and_Audience_Scores[[#This Row],[Audience_Rating]] -> -4 | X51: =FLOOR(Top_500_Movies_Ranked_by_Combined_Critics_and_Audience_Scores[[#This Row],[Year]],10) -> 1990
A52: 51 | B52: Back to the Future | C52: 1985 | D52: Adventure, Comedy, Science Fiction | E52: Robert Zemeckis | F52: en | G52: Won 1 Oscar. Another 18 wins & 24 nominations. | H52: Universal Pictures | I52: 88 | J52: 8.5 | K52: 85 | L52: 1367504 | M52: 87 | N52: 89 | O52: 79 | P52: 91 | Q52: 1322805 | R52: 84 | S52: 1773760 | T52: 93 | U52: itunes, amzvid | V52: 88.17 | W52: =Top_500_Movies_Ranked_by_Combined_Critics_and_Audience_Scores[[#This Row],[Critic_Rating_RT]]-Top_500_Movies_Ranked_by_Combined_Critics_and_Audience_Scores[[#This Row],[Audience_Rating]] -> -2 | X52: =FLOOR(Top_500_Movies_Ranked_by_Combined_Critics_and_Audience_Scores[[#This Row],[Year]],10) -> 1980
A53: 52 | B53: Taxi Driver | C53: 1976 | D53: Crime, Drama | E53: Martin Scorsese | F53: en | G53: Nominated for 4 Oscars. Another 27 wins & 9 nominations. | H53: Columbia Pictures | I53: 87 | J53: 8.2 | K53: 82 | L53: 970967 | M53: 94 | N53: 92 | O53: 103 | P53: 90 | Q53: 719732 | R53: 82 | S53: 1635079 | T53: 88 | U53: itunes, amzvid | V53: 88 | W53: =Top_500_Movies_Ranked_by_Combined_Critics_and_Audience_Scores[[#This Row],[Critic_Rating_RT]]-Top_500_Movies_Ranked_by_Combined_Critics_and_Audience_Scores[[#This Row],[Audience_Rating]] -> 2 | X53: =FLOOR(Top_500_Movies_Ranked_by_Combined_Critics_and_Audience_Scores[[#This Row],[Year]],10) -> 1970
A54: 53 | B54: Touch of Evil | C54: 1958 | D54: Crime, Thriller, Mystery, Drama | E54: Orson Welles | F54: en | I54: 87 | J54: 7.9 | K54: 79 | L54: 112253 | M54: 99 | N54: 92 | O54: 64 | P54: 88 | Q54: 49794 | R54: 84 | S54: 86695 | T54: 86 | U54: itunes, amzvid | V54: 88 | W54: =Top_500_Movies_Ranked_by_Combined_Critics_and_Audience_Scores[[#This Row],[Critic_Rating_RT]]-Top_500_Movies_Ranked_by_Combined_Critics_and_Audience_Scores[[#This Row],[Audience_Rating]] -> 4 | X54: =FLOOR(Top_500_Movies_Ranked_by_Combined_Critics_and_Audience_Scores[[#This Row],[Year]],10) -> 1950
A55: 54 | B55: The Pianist | C55: 2002 | D55: Drama, War | E55: Roman Polanski | F55: en | G55: Won 3 Oscars. Another 50 wins & 61 nominations. | H55: Focus Features | I55: 87 | J55: 8.5 | K55: 85 | L55: 961695 | M55: 85 | N55: 83 | O55: 104 | P55: 93 | Q55: 457473 | R55: 88 | S55: 864540 | T55: 94 | U55: amzvid | V55: 88 | W55: =Top_500_Movies_Ranked_by_Combined_Critics_and_Audience_Scores[[#This Row],[Critic_Rating_RT]]-Top_500_Movies_Ranked_by_Combined_Critics_and_Audience_Scores[[#This Row],[Audience_Rating]] -> -10 | X55: =FLOOR(Top_500_Movies_Ranked_by_Combined_Critics_and_Audience_Scores[[#This Row],[Year]],10) -> 2000
A56: 55 | B56: Toy Story | C56: 1995 | D56: Animation, Adventure, Family, Comedy | E56: John Lasseter | F56: en | G56: Nominated for 3 Oscars. Another 23 wins & 14 nominations. | H56: Buena Vista | I56: 88 | J56: 8.3 | K56: 83 | L56: 1115033 | M56: 96 | N56: 92 | O56: 73 | P56: 89 | Q56: 1290101 | R56: 82 | S56: 1651887 | T56: 86 | U56: disney, itunes, amzvid | V56: 88 | W56: =Top_500_Movies_Ranked_by_Combined_Critics_and_Audience_Scores[[#This Row],[Critic_Rating_RT]]-Top_500_Movies_Ranked_by_Combined_Critics_and_Audience_Scores[[#This Row],[Audience_Rating]] -> 3 | X56: =FLOOR(Top_500_Movies_Ranked_by_Combined_Critics_and_Audience_Scores[[#This Row],[Year]],10) -> 1990
A57: 56 | B57: Raiders of the Lost Ark | C57: 1981 | D57: Adventure, Action | E57: Steven Spielberg | F57: en | G57: Won 4 Oscars. Another 28 wins & 22 nominations. | H57: Paramount Pictures | I57: 88 | J57: 8.4 | K57: 84 | L57: 1068716 | M57: 86 | N57: 91 | O57: 105 | P57: 91 | Q57: 869164 | R57: 84 | S57: 949820 | T57: 91 | U57: disney, paramount, itunes, amzvid | V57: 87.83 | W57: =Top_500_Movies_Ranked_by_Combined_Critics_and_Audience_Scores[[#This Row],[Critic_Rating_RT]]-Top_500_Movies_Ranked_by_Combined_Critics_and_Audience_Scores[[#This Row],[Audience_Rating]] -> 0 | X57: =FLOOR(Top_500_Movies_Ranked_by_Combined_Critics_and_Audience_Scores[[#This Row],[Year]],10) -> 1980
A58: 57 | B58: The Lives of Others | C58: 2006 | D58: Drama, Thriller | E58: Florian Henckel von Donnersmarck | F58: de | G58: Won 1 Oscar. Another 79 wins & 27 nominations. | H58: Sony Pictures Classics | I58: 87 | J58: 8.4 | K58: 84 | L58: 425676 | M58: 89 | N58: 85 | O58: 91 | P58: 92 | Q58: 131607 | R58: 86 | S58: 151084 | T58: 91 | U58: itunes, amzvid | V58: 87.83 | W58: =Top_500_Movies_Ranked_by_Combined_Critics_and_Audience_Scores[[#This Row],[Critic_Rating_RT]]-Top_500_Movies_Ranked_by_Combined_Critics_and_Audience_Scores[[#This Row],[Audience_Rating]] -> -7 | X58: =FLOOR(Top_500_Movies_Ranked_by_Combined_Critics_and_Audience_Scores[[#This Row],[Year]],10) -> 2000
A59: 58 | B59: The Best Years of Our Lives | C59: 1946 | D59: Drama, Romance, War | E59: William Wyler | F59: en | G59: Won 7 Oscars. Another 14 wins & 1 nomination. | H59: RKO Radio Pictures | I59: 87 | J59: 8.1 | K59: 81 | L59: 73744 | M59: 93 | N59: 91 | O59: 63 | P59: 89 | Q59: 20090 | R59: 84 | S59: 38366 | T59: 89 | U59: prime, amzvid | V59: 87.83 | W59: =Top_500_Movies_Ranked_by_Combined_Critics_and_Audience_Scores[[#This Row],[Critic_Rating_RT]]-Top_500_Movies_Ranked_by_Combined_Critics_and_Audience_Scores[[#This Row],[Audience_Rating]] -> 2 | X59: =FLOOR(Top_500_Movies_Ranked_by_Combined_Critics_and_Audience_Scores[[#This Row],[Year]],10) -> 1940
A60: 59 | B60: The Shop Around the Corner | C60: 1940 | D60: Comedy, Drama, Romance | E60: Ernst Lubitsch | F60: en | G60: 1 win. | H60: MGM | I60: 87 | J60: 8 | K60: 80 | L60: 41339 | M60: 96 | N60: 90 | O60: 51 | P60: 88 | Q60: 30945 | R60: 84 | S60: 68741 | T60: 89 | U60: itunes, amzvid, hbm | V60: 87.83 | W60: =Top_500_Movies_Ranked_by_Combined_Critics_and_Audience_Scores[[#This Row],[Critic_Rating_RT]]-Top_500_Movies_Ranked_by_Combined_Critics_and_Audience_Scores[[#This Row],[Audience_Rating]] -> 2 | X60: =FLOOR(Top_500_Movies_Ranked_by_Combined_Critics_and_Audience_Scores[[#This Row],[Year]],10) -> 1940
A61: 60 | B61: There Will Be Blood | C61: 2007 | D61: Drama | E61: Paul Thomas Anderson | F61: en | G61: Won 2 Oscars. Another 117 wins & 101 nominations. | H61: Paramount Vantage | I61: 88 | J61: 8.2 | K61: 82 | L61: 666631 | M61: 93 | N61: 87 | O61: 166 | P61: 84 | Q61: 462225 | R61: 90 | S61: 874342 | T61: 91 | U61: paramount, itunes, amzvid | V61: 87.83 | W61: =Top_500_Movies_Ranked_by_Combined_Critics_and_Audience_Scores[[#This Row],[Critic_Rating_RT]]-Top_500_Movies_Ranked_by_Combined_Critics_and_Audience_Scores[[#This Row],[Audience_Rating]] -> 3 | X61: =FLOOR(Top_500_Movies_Ranked_by_Combined_Critics_and_Audience_Scores[[#This Row],[Year]],10) -> 2000
A62: 61 | B62: The Seventh Seal | C62: 1957 | D62: Fantasy, Drama | E62: Ingmar Bergman | F62: sv | G62: 7 wins & 1 nomination. | H62: Janus Films | I62: 87 | J62: 8.1 | K62: 81 | L62: 206854 | M62: 88 | N62: 91 | O62: 57 | P62: 90 | Q62: 132192 | R62: 86 | S62: 297436 | T62: 90 | U62: itunes, amzvid, hbm | V62: 87.67 | W62: =Top_500_Movies_Ranked_by_Combined_Critics_and_Audience_Scores[[#This Row],[Critic_Rating_RT]]-Top_500_Movies_Ranked_by_Combined_Critics_and_Audience_Scores[[#This Row],[Audience_Rating]] -> 1 | X62: =FLOOR(Top_500_Movies_Ranked_by_Combined_Critics_and_Audience_Scores[[#This Row],[Year]],10) -> 1950
A63: 62 | B63: The Lord of the Rings: The Two Towers | C63: 2002 | D63: Adventure, Fantasy, Action | E63: Peter Jackson | F63: en | G63: Won 2 Oscars. Another 103 wins & 100 nominations. | H63: New Line Cinema | I63: 87 | J63: 8.8 | K63: 88 | L63: 1861078 | M63: 87 | N63: 86 | O63: 140 | P63: 92 | Q63: 1379232 | R63: 88 | S63: 1454840 | T63: 85 | U63: hbo, itunes, amzvid, hbm | V63: 87.67 | W63: =Top_500_Movies_Ranked_by_Combined_Critics_and_Audience_Scores[[#This Row],[Critic_Rating_RT]]-Top_500_Movies_Ranked_by_Combined_Critics_and_Audience_Scores[[#This Row],[Audience_Rating]] -> -6 | X63: =FLOOR(Top_500_Movies_Ranked_by_Combined_Critics_and_Audience_Scores[[#This Row],[Year]],10) -> 2000
A64: 63 | B64: Do the Right Thing | C64: 1989 | D64: Drama | E64: Spike Lee | F64: en | G64: Nominated for 2 Oscars. Another 15 wins & 8 nominations. | H64: Universal Pictures | I64: 88 | J64: 8 | K64: 80 | L64: 117516 | M64: 93 | N64: 92 | O64: 82 | P64: 86 | Q64: 177459 | R64: 88 | S64: 384341 | T64: 86 | U64: prime, itunes, amzvid | V64: 87.5 | W64: =Top_500_Movies_Ranked_by_Combined_Critics_and_Audience_Scores[[#This Row],[Critic_Rating_RT]]-Top_500_Movies_Ranked_by_Combined_Critics_and_Audience_Scores[[#This Row],[Audience_Rating]] -> 6 | X64: =FLOOR(Top_500_Movies_Ranked_by_Combined_Critics_and_Audience_Scores[[#This Row],[Year]],10) -> 1980
A65: 64 | B65: Amadeus | C65: 1984 | D65: History, Music, Drama | E65: Miloš Forman | F65: en | G65: Won 8 Oscars. Another 34 wins & 13 nominations. | H65: Warner Bros. Pictures | I65: 87 | J65: 8.4 | K65: 84 | L65: 446044 | M65: 87 | N65: 89 | O65: 85 | P65: 91 | Q65: 240893 | R65: 86 | S65: 361671 | T65: 88 | U65: itunes, amzvid | V65: 87.5 | W65: =Top_500_Movies_Ranked_by_Combined_Critics_and_Audience_Scores[[#This Row],[Critic_Rating_RT]]-Top_500_Movies_Ranked_by_Combined_Critics_and_Audience_Scores[[#This Row],[Audience_Rating]] -> -2 | X65: =FLOOR(Top_500_Movies_Ranked_by_Combined_Critics_and_Audience_Scores[[#This Row],[Year]],10) -> 1980
A66: 65 | B66: Eternal Sunshine of the Spotless Mind | C66: 2004 | D66: Science Fiction, Drama, Romance | E66: Michel Gondry | F66: en | G66: Won 1 Oscar. Another 71 wins & 68 nominations. | H66: Focus Features | I66: 87 | J66: 8.3 | K66: 83 | L66: 1129606 | M66: 89 | N66: 86 | O66: 165 | P66: 90 | Q66: 1168654 | R66: 84 | S66: 2359950 | T66: 93 | U66: itunes, amzvid | V66: 87.5 | W66: =Top_500_Movies_Ranked_by_Combined_Critics_and_Audience_Scores[[#This Row],[Critic_Rating_RT]]-Top_500_Movies_Ranked_by_Combined_Critics_and_Audience_Scores[[#This Row],[Audience_Rating]] -> -4 | X66: =FLOOR(Top_500_Movies_Ranked_by_Combined_Critics_and_Audience_Scores[[#This Row],[Year]],10) -> 2000
... A68: 67 | B68: Ratatouille | C68: 2007 | D68: Animation, Comedy, Family, Fantasy | E68: Brad Bird | F68: en | G68: Won 1 Oscar. Another 65 wins & 37 nominations. | H68: Disney/Pixar | I68: 87 | J68: 8.1 | K68: 81 | L68: 877175 | M68: 96 | N68: 88 | O68: 152 | P68: 84 | Q68: 1516553 | R68: 84 | S68: 2402281 | T68: 91 | U68: disney, itunes, amzvid | V68: 87.33 | W68: =Top_500_Movies_Ranked_by_Combined_Critics_and_Audience_Scores[[#This Row],[Critic_Rating_RT]]-Top_500_Movies_Ranked_by_Combined_Critics_and_Audience_Scores[[#This Row],[Audience_Rating]] -> 4 | X68: =FLOOR(Top_500_Movies_Ranked_by_Combined_Critics_and_Audience_Scores[[#This Row],[Year]],10) -> 2000
A69: 68 | B69: Past Lives | C69: 2023 | D69: Drama, Romance | E69: Celine Song | F69: en | I69: 87 | J69: 7.8 | K69: 78 | L69: 148063 | M69: 94 | N69: 92 | O69: 181 | Q69: 422095 | R69: 84 | S69: 1258872 | T69: 88 | V69: 87.2 | W69: =Top_500_Movies_Ranked_by_Combined_Critics_and_Audience_Scores[[#This Row],[Critic_Rating_RT]]-Top_500_Movies_Ranked_by_Combined_Critics_and_Audience_Scores[[#This Row],[Audience_Rating]] -> 92 | X69: =FLOOR(Top_500_Movies_Ranked_by_Combined_Critics_and_Audience_Scores[[#This Row],[Year]],10) -> 2020
A70: 69 | B70: The Departed | C70: 2006 | D70: Drama, Thriller, Crime | E70: Martin Scorsese | F70: en | G70: Won 4 Oscars. Another 102 wins & 88 nominations. | H70: Warner Bros. Pictures | I70: 86 | J70: 8.5 | K70: 85 | L70: 1478709 | M70: 85 | N70: 84 | O70: 172 | P70: 91 | Q70: 853886 | R70: 86 | S70: 1082954 | T70: 92 | U70: itunes, amzvid, hbm | V70: 87.17 | W70: =Top_500_Movies_Ranked_by_Combined_Critics_and_Audience_Scores[[#This Row],[Critic_Rating_RT]]-Top_500_Movies_Ranked_by_Combined_Critics_and_Audience_Scores[[#This Row],[Audience_Rating]] -> -7 | X70: =FLOOR(Top_500_Movies_Ranked_by_Combined_Critics_and_Audience_Scores[[#This Row],[Year]],10) -> 2000
A71: 70 | B71: Chinatown | C71: 1974 | D71: Crime, Drama, Mystery, Thriller | E71: Roman Polanski | F71: en | G71: Won 1 Oscar. Another 21 wins & 22 nominations. | H71: Paramount Pictures | I71: 87 | J71: 8.1 | K71: 81 | L71: 362976 | M71: 92 | N71: 94 | O71: 63 | P71: 89 | Q71: 176581 | R71: 86 | S71: 373349 | T71: 81 | U71: paramount, itunes, amzvid, hbm | V71: 87.17 | W71: =Top_500_Movies_Ranked_by_Combined_Critics_and_Audience_Scores[[#This Row],[Critic_Rating_RT]]-Top_500_Movies_Ranked_by_Combined_Critics_and_Audience_Scores[[#This Row],[Audience_Rating]] -> 5 | X71: =FLOOR(Top_500_Movies_Ranked_by_Combined_Critics_and_Audience_Scores[[#This Row],[Year]],10) -> 1970
A72: 71 | B72: Paths of Glory | C72: 1957 | D72: War, Drama, History | E72: Stanley Kubrick | F72: en | G72: Nominated for 1 BAFTA Film Award. Another 4 wins & 2 nominations. | H72: United Artists | I72: 86 | J72: 8.4 | K72: 84 | L72: 224612 | M72: 90 | N72: 90 | O72: 68 | P72: 92 | Q72: 99118 | R72: 88 | S72: 226166 | T72: 79 | U72: itunes, amzvid | V72: 87.17 | W72: =Top_500_Movies_Ranked_by_Combined_Critics_and_Audience_Scores[[#This Row],[Critic_Rating_RT]]-Top_500_Movies_Ranked_by_Combined_Critics_and_Audience_Scores[[#This Row],[Audience_Rating]] -> -2 | X72: =FLOOR(Top_500_Movies_Ranked_by_Combined_Critics_and_Audience_Scores[[#This Row],[Year]],10) -> 1950
A73: 72 | B73: Monty Python and the Holy Grail | C73: 1975 | D73: Adventure, Comedy, Fantasy | E73: Terry Jones, Terry Gilliam | F73: en | G73: 1 win & 2 nominations. | H73: Almi Cinema 5 | I73: 86 | J73: 8.2 | K73: 82 | L73: 584895 | M73: 91 | N73: 87 | O73: 60 | P73: 90 | Q73: 602159 | R73: 82 | S73: 515943 | T73: 91 | U73: britbox, prime, peacock, itunes, amzvid | V73: 87.17 | W73: =Top_500_Movies_Ranked_by_Combined_Critics_and_Audience_Scores[[#This Row],[Critic_Rating_RT]]-Top_500_Movies_Ranked_by_Combined_Critics_and_Audience_Scores[[#This Row],[Audience_Rating]] -> -3 | X73: =FLOOR(Top_500_Movies_Ranked_by_Combined_Critics_and_Audience_Scores[[#This Row],[Year]],10) -> 1970
A74: 73 | B74: My Neighbor Totoro | C74: 1988 | D74: Fantasy, Animation, Family | E74: Hayao Miyazaki | F74: ja | G74: 5 wins & 1 nomination. | H74: Tokuma Shoten | I74: 86 | J74: 8.1 | K74: 81 | L74: 403332 | M74: 87 | N74: 86 | O74: 54 | P74: 90 | Q74: 503212 | R74: 84 | S74: 1326860 | T74: 94 | U74: itunes, amzvid, hbm | V74: 87 | W74: =Top_500_Movies_Ranked_by_Combined_Critics_and_Audience_Scores[[#This Row],[Critic_Rating_RT]]-Top_500_Movies_Ranked_by_Combined_Critics_and_Audience_Scores[[#This Row],[Audience_Rating]] -> -4 | X74: =FLOOR(Top_500_Movies_Ranked_by_Combined_Critics_and_Audience_Scores[[#This Row],[Year]],10) -> 1980
A75: 74 | B75: L.A. Confidential | C75: 1997 | D75: Crime, Mystery, Thriller, Drama | E75: Curtis Hanson | F75: en | G75: Won 2 Oscars. Another 95 wins & 62 nominations. | H75: Warner Bros. Pictures | I75: 86 | J75: 8.2 | K75: 82 | L75: 638085 | M75: 91 | N75: 90 | O75: 96 | P75: 90 | Q75: 205235 | R75: 82 | S75: 312718 | T75: 87 | U75: hulu, disney, prime | V75: 87 | W75: =Top_500_Movies_Ranked_by_Combined_Critics_and_Audience_Scores[[#This Row],[Critic_Rating_RT]]-Top_500_Movies_Ranked_by_Combined_Critics_and_Audience_Scores[[#This Row],[Audience_Rating]] -> 0 | X75: =FLOOR(Top_500_Movies_Ranked_by_Combined_Critics_and_Audience_Scores[[#This Row],[Year]],10) -> 1990
A76: 75 | B76: The Lion King | C76: 1994 | D76: Family, Animation, Drama | E76: Roger Allers, Rob Minkoff | F76: en | G76: Won 2 Oscars. Another 28 wins & 25 nominations. | H76: Buena Vista | I76: 86 | J76: 8.5 | K76: 85 | L76: 1194520 | M76: 88 | N76: 86 | O76: 115 | P76: 90 | Q76: 1332919 | R76: 84 | S76: 1460091 | T76: 89 | U76: disney, itunes, amzvid | V76: 87 | W76: =Top_500_Movies_Ranked_by_Combined_Critics_and_Audience_Scores[[#This Row],[Critic_Rating_RT]]-Top_500_Movies_Ranked_by_Combined_Critics_and_Audience_Scores[[#This Row],[Audience_Rating]] -> -4 | X76: =FLOOR(Top_500_Movies_Ranked_by_Combined_Critics_and_Audience_Scores[[#This Row],[Year]],10) -> 1990
A77: 76 | B77: Hamilton | C77: 2020 | D77: History, Drama | E77: Thomas Kail | F77: en | I77: 87 | J77: 8.3 | K77: 83 | L77: 126439 | M77: 88 | N77: 91 | O77: 102 | P77: 88 | Q77: 142644 | R77: 84 | S77: 423181 | T77: 87 | V77: 86.83 | W77: =Top_500_Movies_Ranked_by_Combined_Critics_and_Audience_Scores[[#This Row],[Critic_Rating_RT]]-Top_500_Movies_Ranked_by_Combined_Critics_and_Audience_Scores[[#This Row],[Audience_Rating]] -> 3 | X77: =FLOOR(Top_500_Movies_Ranked_by_Combined_Critics_and_Audience_Scores[[#This Row],[Year]],10) -> 2020
A78: 77 | B78: Cinema Paradiso | C78: 1988 | D78: Drama, Romance | E78: Giuseppe Tornatore | F78: it | G78: Won 1 Oscar. Another 20 wins & 23 nominations. | H78: Miramax Films | I78: 86 | J78: 8.5 | K78: 85 | L78: 299114 | M78: 80 | N78: 81 | O78: 61 | P78: 93 | Q78: 156145 | R78: 90 | S78: 336814 | T78: 92 | U78: itunes, amzvid | V78: 86.83 | W78: =Top_500_Movies_Ranked_by_Combined_Critics_and_Audience_Scores[[#This Row],[Critic_Rating_RT]]-Top_500_Movies_Ranked_by_Combined_Critics_and_Audience_Scores[[#This Row],[Audience_Rating]] -> -12 | X78: =FLOOR(Top_500_Movies_Ranked_by_Combined_Critics_and_Audience_Scores[[#This Row],[Year]],10) -> 1980
A79: 78 | B79: City of God | C79: 2002 | D79: Drama, Crime | E79: Fernando Meirelles | F79: pt | G79: Nominated for 4 Oscars. Another 70 wins & 29 nominations. | H79: Miramax Films | I79: 86 | J79: 8.6 | K79: 86 | L79: 832918 | M79: 79 | N79: 82 | O79: 110 | P79: 93 | Q79: 417654 | R79: 90 | S79: 747463 | T79: 91 | U79: itunes, amzvid | V79: 86.83 | W79: =Top_500_Movies_Ranked_by_Combined_Critics_and_Audience_Scores[[#This Row],[Critic_Rating_RT]]-Top_500_Movies_Ranked_by_Combined_Critics_and_Audience_Scores[[#This Row],[Audience_Rating]] -> -11 | X79: =FLOOR(Top_500_Movies_Ranked_by_Combined_Critics_and_Audience_Scores[[#This Row],[Year]],10) -> 2000
A80: 79 | B80: Wolfwalkers | C80: 2020 | D80: Animation, Family, Adventure, Fantasy | E80: Tomm Moore, Ross Stewart | F80: en | I80: 85 | J80: 8 | K80: 80 | L80: 41605 | M80: 87 | N80: 87 | O80: 109 | P80: 95 | Q80: 45817 | R80: 84 | S80: 135079 | T80: 88 | U80: apple | V80: 86.83 | W80: =Top_500_Movies_Ranked_by_Combined_Critics_and_Audience_Scores[[#This Row],[Critic_Rating_RT]]-Top_500_Movies_Ranked_by_Combined_Critics_and_Audience_Scores[[#This Row],[Audience_Rating]] -> -8 | X80: =FLOOR(Top_500_Movies_Ranked_by_Combined_Critics_and_Audience_Scores[[#This Row],[Year]],10) -> 2020
A81: 80 | B81: The Bridge on the River Kwai | C81: 1957 | D81: Drama, History, War | E81: David Lean | F81: en | G81: Won 7 Oscars. Another 23 wins & 7 nominations. | H81: Columbia Pictures | I81: 87 | J81: 8.1 | K81: 81 | L81: 240528 | M81: 88 | N81: 93 | O81: 64 | P81: 89 | Q81: 67210 | R81: 84 | S81: 91805 | T81: 86 | U81: itunes, amzvid, hbm | V81: 86.83 | W81: =Top_500_Movies_Ranked_by_Combined_Critics_and_Audience_Scores[[#This Row],[Critic_Rating_RT]]-Top_500_Movies_Ranked_by_Combined_Critics_and_Audience_Scores[[#This Row],[Audience_Rating]] -> 4 | X81: =FLOOR(Top_500_Movies_Ranked_by_Combined_Critics_and_Audience_Scores[[#This Row],[Year]],10) -> 1950
A82: 81 | B82: I'm Still Here | C82: 2024 | D82: Drama, History | E82: Walter Salles | F82: pt | I82: 87 | J82: 8.4 | K82: 84 | L82: 94661 | M82: 85 | N82: 84 | O82: 106 | R82: 86 | S82: 526291 | T82: 95 | U82: netflix | V82: 86.8 | W82: =Top_500_Movies_Ranked_by_Combined_Critics_and_Audience_Scores[[#This Row],[Critic_Rating_RT]]-Top_500_Movies_Ranked_by_Combined_Critics_and_Audience_Scores[[#This Row],[Audience_Rating]] -> 84 | X82: =FLOOR(Top_500_Movies_Ranked_by_Combined_Critics_and_Audience_Scores[[#This Row],[Year]],10) -> 2020
A83: 82 | B83: It Happened One Night | C83: 1934 | D83: Comedy, Romance | E83: Frank Capra | F83: en | G83: Won 5 Oscars. Another 5 wins & 1 nomination. | H83: Sony Pictures Home Entertainment | I83: 86 | J83: 8.1 | K83: 81 | L83: 116269 | M83: 87 | N83: 90 | O83: 72 | P83: 89 | Q83: 56458 | R83: 84 | S83: 101589 | T83: 89 | U83: itunes, amzvid | V83: 86.67 | W83: =Top_500_Movies_Ranked_by_Combined_Critics_and_Audience_Scores[[#This Row],[Critic_Rating_RT]]-Top_500_Movies_Ranked_by_Combined_Critics_and_Audience_Scores[[#This Row],[Audience_Rating]] -> 1 | X83: =FLOOR(Top_500_Movies_Ranked_by_Combined_Critics_and_Audience_Scores[[#This Row],[Year]],10) -> 1930
A84: 83 | B84: Beauty and the Beast | C84: 1991 | D84: Romance, Family, Animation, Fantasy | E84: Gary Trousdale, Kirk Wise | F84: en | G84: Won 2 Oscars. Another 22 wins & 20 nominations. | H84: Buena Vista | I84: 86 | J84: 8 | K84: 80 | L84: 491091 | M84: 95 | N84: 89 | O84: 102 | P84: 88 | Q84: 679535 | R84: 78 | S84: 640107 | T84: 90 | U84: disney, itunes, amzvid | V84: 86.67 | W84: =Top_500_Movies_Ranked_by_Combined_Critics_and_Audience_Scores[[#This Row],[Critic_Rating_RT]]-Top_500_Movies_Ranked_by_Combined_Critics_and_Audience_Scores[[#This Row],[Audience_Rating]] -> 1 | X84: =FLOOR(Top_500_Movies_Ranked_by_Combined_Critics_and_Audience_Scores[[#This Row],[Year]],10) -> 1990
A85: 84 | B85: Spider-Man: Into the Spider-Verse | C85: 2018 | D85: Animation, Action, Adventure, Science Fiction | E85: Bob Persichetti, Peter Ramsey, Rodney Rothman | F85: en | I85: 86 | J85: 8.4 | K85: 84 | L85: 723333 | M85: 87 | N85: 88 | O85: 242 | P85: 90 | Q85: 1068834 | R85: 88 | S85: 3153094 | T85: 83 | U85: netflix, itunes, amzvid | V85: 86.67 | W85: =Top_500_Movies_Ranked_by_Combined_Critics_and_Audience_Scores[[#This Row],[Critic_Rating_RT]]-Top_500_Movies_Ranked_by_Combined_Critics_and_Audience_Scores[[#This Row],[Audience_Rating]] -> -2 | X85: =FLOOR(Top_500_Movies_Ranked_by_Combined_Critics_and_Audience_Scores[[#This Row],[Year]],10) -> 2010
A86: 85 | B86: 8½ | C86: 1963 | D86: Drama | E86: Federico Fellini | F86: it | G86: Won 2 Oscars. Another 16 wins & 8 nominations. | H86: Cinerez | I86: 86 | J86: 8 | K86: 80 | L86: 128719 | M86: 93 | N86: 87 | O86: 53 | P86: 89 | Q86: 95771 | R86: 86 | S86: 196861 | T86: 85 | U86: itunes, amzvid, hbm | V86: 86.67 | W86: =Top_500_Movies_Ranked_by_Combined_Critics_and_Audience_Scores[[#This Row],[Critic_Rating_RT]]-Top_500_Movies_Ranked_by_Combined_Critics_and_Audience_Scores[[#This Row],[Audience_Rating]] -> -2 | X86: =FLOOR(Top_500_Movies_Ranked_by_Combined_Critics_and_Audience_Scores[[#This Row],[Year]],10) -> 1960
A87: 86 | B87: Spider-Man: Across the Spider-Verse | C87: 2023 | D87: Animation, Action, Adventure, Science Fiction | E87: Kemp Powers, Justin K. Thompson, Joaquim Dos Santos | F87: en | I87: 87 | J87: 8.5 | K87: 85 | L87: 441825 | M87: 86 | N87: 86 | O87: 222 | Q87: 838214 | R87: 88 | S87: 2432408 | T87: 88 | U87: disney | V87: 86.6 | W87: =Top_500_Movies_Ranked_by_Combined_Critics_and_Audience_Scores[[#This Row],[Critic_Rating_RT]]-Top_500_Movies_Ranked_by_Combined_Critics_and_Audience_Scores[[#This Row],[Audience_Rating]] -> 86 | X87: =FLOOR(Top_500_Movies_Ranked_by_Combined_Critics_and_Audience_Scores[[#This Row],[Year]],10) -> 2020
A88: 87 | B88: The Wild Robot | C88: 2024 | D88: Animation, Science Fiction, Family | E88: Chris Sanders | F88: en | I88: 87 | J88: 8.2 | K88: 82 | L88: 151761 | M88: 85 | N88: 84 | O88: 143 | R88: 84 | S88: 807351 | T88: 98 | U88: peacock | V88: 86.6 | W88: =Top_500_Movies_Ranked_by_Combined_Critics_and_Audience_Scores[[#This Row],[Critic_Rating_RT]]-Top_500_Movies_Ranked_by_Combined_Critics_and_Audience_Scores[[#This Row],[Audience_Rating]] -> 84 | X88: =FLOOR(Top_500_Movies_Ranked_by_Combined_Critics_and_Audience_Scores[[#This Row],[Year]],10) -> 2020
A89: 88 | B89: Gone with the Wind | C89: 1939 | D89: Drama, War, Romance | E89: Victor Fleming | F89: en | G89: Won 8 Oscars. Another 11 wins & 6 nominations. | H89: Loew's Inc. | I89: 86 | J89: 8.2 | K89: 82 | L89: 344610 | M89: 97 | N89: 90 | O89: 66 | P89: 88 | Q89: 259241 | R89: 78 | S89: 189395 | T89: 84 | U89: hbo, itunes, amzvid, hbm | V89: 86.5 | W89: =Top_500_Movies_Ranked_by_Combined_Critics_and_Audience_Scores[[#This Row],[Critic_Rating_RT]]-Top_500_Movies_Ranked_by_Combined_Critics_and_Audience_Scores[[#This Row],[Audience_Rating]] -> 2 | X89: =FLOOR(Top_500_Movies_Ranked_by_Combined_Critics_and_Audience_Scores[[#This Row],[Year]],10) -> 1930
A90: 89 | B90: The Wild Bunch | C90: 1969 | D90: Western | E90: Sam Peckinpah | F90: en | G90: Nominated for 2 Oscars. Another 6 wins & 3 nominations. | H90: Warner Bros. Pictures | I90: 86 | J90: 7.9 | K90: 79 | L90: 92654 | M90: 98 | N90: 91 | O90: 54 | P90: 87 | Q90: 43809 | R90: 82 | S90: 62739 | T90: 82 | U90: itunes, amzvid | V90: 86.5 | W90: =Top_500_Movies_Ranked_by_Combined_Critics_and_Audience_Scores[[#This Row],[Critic_Rating_RT]]-Top_500_Movies_Ranked_by_Combined_Critics_and_Audience_Scores[[#This Row],[Audience_Rating]] -> 4 | X90: =FLOOR(Top_500_Movies_Ranked_by_Combined_Critics_and_Audience_Scores[[#This Row],[Year]],10) -> 1960
A91: 90 | B91: In the Mood for Love | C91: 2000 | D91: Drama, Romance | E91: Wong Kar-wai | F91: cn | G91: Nominated for 1 BAFTA Film Award. Another 43 wins & 38 nominations. | H91: USA Films | I91: 85 | J91: 8.1 | K91: 81 | L91: 175775 | M91: 87 | N91: 82 | O91: 87 | P91: 90 | Q91: 251393 | R91: 88 | S91: 645707 | T91: 91 | U91: hbm | V91: 86.5 | W91: =Top_500_Movies_Ranked_by_Combined_Critics_and_Audience_Scores[[#This Row],[Critic_Rating_RT]]-Top_500_Movies_Ranked_by_Combined_Critics_and_Audience_Scores[[#This Row],[Audience_Rating]] -> -8 | X91: =FLOOR(Top_500_Movies_Ranked_by_Combined_Critics_and_Audience_Scores[[#This Row],[Year]],10) -> 2000
A92: 91 | B92: Toy Story 3 | C92: 2010 | D92: Animation, Family, Comedy | E92: Lee Unkrich | F92: en | G92: Won 2 Oscars. Another 61 wins & 81 nominations. | H92: Walt Disney Pictures | I92: 86 | J92: 8.3 | K92: 83 | L92: 926157 | M92: 92 | N92: 90 | O92: 218 | P92: 86 | Q92: 796262 | R92: 80 | S92: 1171417 | T92: 88 | U92: disney, itunes, amzvid | V92: 86.5 | W92: =Top_500_Movies_Ranked_by_Combined_Critics_and_Audience_Scores[[#This Row],[Critic_Rating_RT]]-Top_500_Movies_Ranked_by_Combined_Critics_and_Audience_Scores[[#This Row],[Audience_Rating]] -> 4 | X92: =FLOOR(Top_500_Movies_Ranked_by_Combined_Critics_and_Audience_Scores[[#This Row],[Year]],10) -> 2010
A93: 92 | B93: The Truman Show | C93: 1998 | D93: Comedy, Drama | E93: Peter Weir | F93: en | G93: Nominated for 3 Oscars. Another 35 wins & 64 nominations. | H93: Paramount Pictures | I93: 86 | J93: 8.2 | K93: 82 | L93: 1267347 | M93: 90 | N93: 86 | O93: 108 | P93: 87 | Q93: 1350393 | R93: 84 | S93: 2880682 | T93: 90 | U93: paramount, itunes, amzvid, hbm | V93: 86.5 | W93: =Top_500_Movies_Ranked_by_Combined_Critics_and_Audience_Scores[[#This Row],[Critic_Rating_RT]]-Top_500_Movies_Ranked_by_Combined_Critics_and_Audience_Scores[[#This Row],[Audience_Rating]] -> -1 | X93: =FLOOR(Top_500_Movies_Ranked_by_Combined_Critics_and_Audience_Scores[[#This Row],[Year]],10) -> 1990
A94: 93 | B94: Fargo | C94: 1996 | D94: Crime, Drama, Thriller | E94: Joel Coen | F94: en | G94: Won 2 Oscars. Another 78 wins & 42 nominations. | H94: MGM | I94: 86 | J94: 8.1 | K94: 81 | L94: 751771 | M94: 88 | N94: 88 | O94: 72 | P94: 89 | Q94: 470077 | R94: 84 | S94: 939939 | T94: 89 | U94: itunes, amzvid | V94: 86.5 | W94: =Top_500_Movies_Ranked_by_Combined_Critics_and_Audience_Scores[[#This Row],[Critic_Rating_RT]]-Top_500_Movies_Ranked_by_Combined_Critics_and_Audience_Scores[[#This Row],[Audience_Rating]] -> -1 | X94: =FLOOR(Top_500_Movies_Ranked_by_Combined_Critics_and_Audience_Scores[[#This Row],[Year]],10) -> 1990
A95: 94 | B95: Shoplifters | C95: 2018 | D95: Drama, Crime, Thriller | E95: Hirokazu Kore-eda | F95: ja | I95: 86 | J95: 7.9 | K95: 79 | L95: 91034 | M95: 93 | N95: 89 | O95: 147 | P95: 88 | Q95: 83143 | R95: 86 | S95: 244423 | T95: 84 | U95: itunes, amzvid | V95: 86.5 | W95: =Top_500_Movies_Ranked_by_Combined_Critics_and_Audience_Scores[[#This Row],[Critic_Rating_RT]]-Top_500_Movies_Ranked_by_Combined_Critics_and_Audience_Scores[[#This Row],[Audience_Rating]] -> 1 | X95: =FLOOR(Top_500_Movies_Ranked_by_Combined_Critics_and_Audience_Scores[[#This Row],[Year]],10) -> 2010
A96: 95 | B96: No Country for Old Men | C96: 2007 | D96: Crime, Drama, Thriller | E96: Joel Coen, Ethan Coen | F96: en | G96: Won 4 Oscars. Another 168 wins & 98 nominations. | H96: Miramax Films | I96: 87 | J96: 8.2 | K96: 82 | L96: 1113836 | M96: 92 | N96: 89 | O96: 206 | P96: 84 | Q96: 743270 | R96: 86 | S96: 1428294 | T96: 85 | U96: prime, paramount, itunes, amzvid, hbm | V96: 86.33 | W96: =Top_500_Movies_Ranked_by_Combined_Critics_and_Audience_Scores[[#This Row],[Critic_Rating_RT]]-Top_500_Movies_Ranked_by_Combined_Critics_and_Audience_Scores[[#This Row],[Audience_Rating]] -> 5 | X96: =FLOOR(Top_500_Movies_Ranked_by_Combined_Critics_and_Audience_Scores[[#This Row],[Year]],10) -> 2000
A97: 96 | B97: Aliens | C97: 1986 | D97: Action, Thriller, Science Fiction | E97: James Cameron | F97: en | G97: Won 2 Oscars. Another 16 wins & 22 nominations. | H97: 20th Century Fox Film Corporat | I97: 86 | J97: 8.4 | K97: 84 | L97: 804533 | M97: 84 | N97: 88 | O97: 99 | P97: 90 | Q97: 516707 | R97: 82 | S97: 687721 | T97: 90 | U97: hbo, itunes, amzvid | V97: 86.33 | W97: =Top_500_Movies_Ranked_by_Combined_Critics_and_Audience_Scores[[#This Row],[Critic_Rating_RT]]-Top_500_Movies_Ranked_by_Combined_Critics_and_Audience_Scores[[#This Row],[Audience_Rating]] -> -2 | X97: =FLOOR(Top_500_Movies_Ranked_by_Combined_Critics_and_Audience_Scores[[#This Row],[Year]],10) -> 1980
A98: 97 | B98: La Dolce Vita | C98: 1960 | D98: Comedy, Drama | E98: Federico Fellini | F98: it | G98: Won 1 Oscar. Another 10 wins & 12 nominations. | H98: American International Picture | I98: 86 | J98: 8 | K98: 80 | L98: 82147 | M98: 95 | N98: 92 | O98: 66 | P98: 87 | Q98: 62176 | R98: 86 | S98: 118064 | T98: 78 | V98: 86.33 | W98: =Top_500_Movies_Ranked_by_Combined_Critics_and_Audience_Scores[[#This Row],[Critic_Rating_RT]]-Top_500_Movies_Ranked_by_Combined_Critics_and_Audience_Scores[[#This Row],[Audience_Rating]] -> 5 | X98: =FLOOR(Top_500_Movies_Ranked_by_Combined_Critics_and_Audience_Scores[[#This Row],[Year]],10) -> 1960
A99: 98 | B99: Once Upon a Time in the West | C99: 1968 | D99: Drama, Western | E99: Sergio Leone | F99: it | G99: 4 wins & 5 nominations. | H99: Paramount Pictures | I99: 86 | J99: 8.5 | K99: 85 | L99: 365674 | M99: 82 | N99: 89 | O99: 61 | P99: 92 | Q99: 112953 | R99: 88 | S99: 206571 | T99: 82 | U99: paramount, itunes, amzvid | V99: 86.33 | W99: =Top_500_Movies_Ranked_by_Combined_Critics_and_Audience_Scores[[#This Row],[Critic_Rating_RT]]-Top_500_Movies_Ranked_by_Combined_Critics_and_Audience_Scores[[#This Row],[Audience_Rating]] -> -3 | X99: =FLOOR(Top_500_Movies_Ranked_by_Combined_Critics_and_Audience_Scores[[#This Row],[Year]],10) -> 1960
A100: 99 | B100: The General | C100: 1926 | D100: Comedy, Action, Adventure, War | E100: Clyde Bruckman, Buster Keaton | F100: en | G100: 2 wins & 1 nomination. | H100: United Artists Films | I100: 86 | J100: 8.1 | K100: 81 | L100: 101941 | N100: 93 | O100: 52 | P100: 89 | Q100: 36906 | R100: 84 | S100: 87490 | T100: 84 | U100: prime, amzvid | V100: 86.2 | W100: =Top_500_Movies_Ranked_by_Combined_Critics_and_Audience_Scores[[#This Row],[Critic_Rating_RT]]-Top_500_Movies_Ranked_by_Combined_Critics_and_Audience_Scores[[#This Row],[Audience_Rating]] -> 4 | X100: =FLOOR(Top_500_Movies_Ranked_by_Combined_Critics_and_Audience_Scores[[#This Row],[Year]],10) -> 1920
A101: 100 | B101: Solaris | C101: 1972 | D101: Drama, Science Fiction, Mystery | E101: Andrei Tarkovsky | F101: ru | G101: 2 wins & 4 nominations. | H101: Kino International | I101: 86 | J101: 7.9 | K101: 79 | L101: 101413 | M101: 93 | N101: 88 | O101: 62 | P101: 87 | Q101: 71458 | R101: 84 | S101: 159749 | T101: 86 | U101: itunes, amzvid, hbm | V101: 86.17 | W101: =Top_500_Movies_Ranked_by_Combined_Critics_and_Audience_Scores[[#This Row],[Critic_Rating_RT]]-Top_500_Movies_Ranked_by_Combined_Critics_and_Audience_Scores[[#This Row],[Audience_Rating]] -> 1 | X101: =FLOOR(Top_500_Movies_Ranked_by_Combined_Critics_and_Audience_Scores[[#This Row],[Year]],10) -> 1970
...

Sheet Analysis
A1: General Statistic
A3: General count of films | B3: =COUNTA(' Clean_data'!B:B) -> 450
A4: Average IMBD raiting | B4: =AVERAGE(' Clean_data'!J:J) -> 7.9694878
A5: Highest IMDB raiting | B5: =MAX(' Clean_data'!J:J) -> 9.2
A6: Lowest IMDB raiting | B6: =MIN(' Clean_data'!J:J) -> 7.1
A7: Average Metacritic | B7: =AVERAGE(' Clean_data'!M:M) -> 86.754587
A10: TOP genres | B10: Count | C10: Average IMDB per genre
A11: Drama | B11: =COUNTIF(' Clean_data'!D:D,"*Drama*") -> 297 | C11: =AVERAGEIF(' Clean_data'!D:D,"*Drama*",' Clean_data'!J:J) -> 7.9424242
A12: Crime | B12: =COUNTIF(' Clean_data'!D:D,"*Crime*") -> 68 | C12: =AVERAGEIF(' Clean_data'!D:D,"*Crime*",' Clean_data'!J:J) -> 8.0117647
A13: Comedy | B13: =COUNTIF(' Clean_data'!D:D,"*Comedy*") -> 88 | C13: =AVERAGEIF(' Clean_data'!D:D,"*Comedy*",' Clean_data'!J:J) -> 7.8772727
A14: Thriller | B14: =COUNTIF(' Clean_data'!D:D,"*Thriller*") -> 92 | C14: =AVERAGEIF(' Clean_data'!D:D,"*Thriller*",' Clean_data'!J:J) -> 7.9706522
A15: Action | B15: =COUNTIF(' Clean_data'!D:D,"*Action*") -> 52 | C15: =AVERAGEIF(' Clean_data'!D:D,"*Action*",' Clean_data'!J:J) -> 8.0807692
A16: Romance | B16: =COUNTIF(' Clean_data'!D:D,"*Romance*") -> 76 | C16: =AVERAGEIF(' Clean_data'!D:D,"*Romance*",' Clean_data'!J:J) -> 7.8986842
A17: Animation | B17: =COUNTIF(' Clean_data'!D:D,"*Animation*") -> 51 | C17: =AVERAGEIF(' Clean_data'!D:D,"*Animation*",' Clean_data'!J:J) -> 7.9921569
A18: War | B18: =COUNTIF(' Clean_data'!D:D,"*War*") -> 30 | C18: =AVERAGEIF(' Clean_data'!D:D,"*War*",' Clean_data'!J:J) -> 8.14
A21: Critics vs Audience
A22: Average gap critics vs audience | B22: =AVERAGE(' Clean_data'!W:W) -> 9
A23: MAX gap(critics higher) | B23: =MAX(' Clean_data'!W:W) -> 92
A24: MAX gap(audience higher) | B24: =MIN(' Clean_data'!W:W) -> -21
A27: Critics LIKE, audience - NO
A28: Film | B28: =INDEX(' Clean_data'!B:B,MATCH(MAX(' Clean_data'!W:W),' Clean_data'!W:W,0)) -> Past Lives
A29: Gap | B29: =MAX(' Clean_data'!W:W) -> 92
A31: Audience LIKES, critics - NO
A32: Film | B32: =INDEX(' Clean_data'!B:B,MATCH(MIN(' Clean_data'!W:W),' Clean_data'!W:W,0)) -> Fight Club
A33: Gap | B33: =MIN(' Clean_data'!W:W) -> -21
A35: Analysis by decade
A36: Decade | B36: Count of films | C36: Average IMDB
A37: 1920 | B37: =COUNTIF(' Clean_data'!X:X,Analysis!A37) -> 4 | C37: =ROUND(AVERAGEIF(' Clean_data'!X:X,Analysis!A37,' Clean_data'!J:J),2) -> 8.05
A38: 1930 | B38: =COUNTIF(' Clean_data'!X:X,Analysis!A38) -> 12 | C38: =ROUND(AVERAGEIF(' Clean_data'!X:X,Analysis!A38,' Clean_data'!J:J),2) -> 8.08
A39: 1940 | B39: =COUNTIF(' Clean_data'!X:X,Analysis!A39) -> 18 | C39: =ROUND(AVERAGEIF(' Clean_data'!X:X,Analysis!A39,' Clean_data'!J:J),2) -> 7.97
A40: 1950 | B40: =COUNTIF(' Clean_data'!X:X,Analysis!A40) -> 25 | C40: =ROUND(AVERAGEIF(' Clean_data'!X:X,Analysis!A40,' Clean_data'!J:J),2) -> 8.16
A41: 1960 | B41: =COUNTIF(' Clean_data'!X:X,Analysis!A41) -> 29 | C41: =ROUND(AVERAGEIF(' Clean_data'!X:X,Analysis!A41,' Clean_data'!J:J),2) -> 7.95
A42: 1970 | B42: =COUNTIF(' Clean_data'!X:X,Analysis!A42) -> 40 | C42: =ROUND(AVERAGEIF(' Clean_data'!X:X,Analysis!A42,' Clean_data'!J:J),2) -> 7.94
A43: 1980 | B43: =COUNTIF(' Clean_data'!X:X,Analysis!A43) -> 27 | C43: =ROUND(AVERAGEIF(' Clean_data'!X:X,Analysis!A43,' Clean_data'!J:J),2) -> 8.09
A44: 1990 | B44: =COUNTIF(' Clean_data'!X:X,Analysis!A44) -> 42 | C44: =ROUND(AVERAGEIF(' Clean_data'!X:X,Analysis!A44,' Clean_data'!J:J),2) -> 8.19
A45: 2000 | B45: =COUNTIF(' Clean_data'!X:X,Analysis!A45) -> 85 | C45: =ROUND(AVERAGEIF(' Clean_data'!X:X,Analysis!A45,' Clean_data'!J:J),2) -> 8.01
A46: 2010 | B46: =COUNTIF(' Clean_data'!X:X,Analysis!A46) -> 115 | C46: =ROUND(AVERAGEIF(' Clean_data'!X:X,Analysis!A46,' Clean_data'!J:J),2) -> 7.88
A47: 2020 | B47: =COUNTIF(' Clean_data'!X:X,Analysis!A47) -> 52 | C47: =ROUND(AVERAGEIF(' Clean_data'!X:X,Analysis!A47,' Clean_data'!J:J),2) -> 7.77

Sheet Dashboard
A2: TOP 450 MOVIES — DATA ANALYSIS
A4: 450 | I4: 7.97 | P4: Best genre - WAR / 8,14 IMDB
A5: Count of films | H5: Average IMDB | O5: Critics vs Audience Rating
E25: KEY FINDINGS:
E26: - 1990s had highest average IMDb rating (8.19)
E27: - Drama is the most common genre
E28: - Fight Club has the biggest gap: audience rates 21pts higher than critics
E29: - 2010s produced the most top-rated films (115)
